Workbook

Sheet A
A1: HOW TO CALCULATE TAXES

Sheet Rates for Tax Calculation
A1: England, Wales, Northern Ireland - Income Tax (Applies to Employment/Self Employment Income/Property Income/Trust Income/Foreign Income)
A3: Band | B3: Taxable Income Range | C3: Rate | E3: Trigger these if Individual home address is in any of these jurisdictions, and if any of the income chosen above is picked by the user upon setup.
A4: Personal Allowance | B4: £0 – £12,570 | C4: 0
A5: Basic Rate | B5: £12,571 – £50,270 | C5: 0.2
A6: Higher Rate | B6: £50,271 – £125,140 | C6: 0.4
A7: Additional Rate | B7: Over £125,140 | C7: 0.45
A9: Note: The Personal Allowance tapers by £1 for every £2 of income over £100,000. It is fully withdrawn at £125,140.
A11: Example 1 | B11: (This is for calculation for users view on daily tax) | F11: Example 2 | G11: (This is for calculation for users view on daily tax)
A13: Employment | B13: 25000 | F13: Employment | G13: 25000
A14: Self Employment | B14: 55000 | F14: Self Employment | G14: 55000
A15: Property Income | B15: 24000 | F15: Property Income | G15: 24000
A16: Total Income | B16: =SUM(B13:B15) -> 104000 | F16: Pension | G16: =-12000*100/80 -> -15000
F17: Total Income less deductions | G17: =SUM(G13:G16) -> 89000
A18: Since income >100k | B18: =(104000-100000)/2 -> 2000 | C18: To take off
A19: Tapered personal allowance | B19: =12570-B18 -> 10570 | F19: Since income <100k full personal allowance given of £12,570
F20: Taxable income | G20: =SUM(G13:G15)-12570 -> 91430
A21: Taxable income | B21: =B16-B19 -> 93430 | F21: Tax | G21: =(50270-12571)*20% -> 7539.8
G22: =(G20-50271)*40% -> 16463.6
A23: Tax | B23: =(50270-12571)*20% -> 7539.8 | G23: =SUM(G21:G22) -> 24003.4
B24: =(B21-50271)*40% -> 17263.6 | F24: Tax deducted at source | G24: =12000+G16 -> -3000
B25: =SUM(B23:B24) -> 24803.4 | G25: =SUM(G23:G24) -> 21003.4
A27: If the users income uses up all the first band just take the upper limit less the lower limit. | F27: So the pension paid by the user, only helps in calculating the personal allowance, and it not being tapered. The only relief available tat will directly reduce your liability is the tax deducted at source.
A28: Then if the remainder then falls into the next 40% band, take the taxable income total less the lower limit > If this had fallen into the additional rate band, then we would have done the same as above.
A30: Scotland - Income Tax (Applies to Employment/Self Employment Income/Property Income/Trust Income/Foreign Income)
A32: Band | B32: Taxable Income Range | C32: Rate | E32: Trigger these if Individual home address is in SCOTLAND ONLY, and if any of the income chosen above is picked by the user upon setup.
A33: Personal Allowance | B33: £0 – £12,570 | C33: 0
A34: Starter Rate | B34: £12,571 – £14,876 | C34: 0.19
A35: Basic Rate | B35: £14,877 – £26,561 | C35: 0.2
A36: Intermediate Rate | B36: £26,562 – £43,662 | C36: 0.21
A37: Higher Rate | B37: £43,663 – £75,000 | C37: 0.42
A38: Advanced Rate | B38: £75,001 – £125,140 | C38: 0.45
A39: Top Rate | B39: Over £125,140 | C39: 0.48
A41: Same rules apply, just different bands.
A44: Dividend Income Rates - Applies to all UK
A46: These rates apply across England, Wales, Northern Ireland, and Scotland.
A47: Band | B47: Band amounts | C47: Tax Rate on Dividends
A48: Dividend Allowance (first £500) | B48: £0 - £500 | C48: 0
A49: Basic Rate | B49: £12,571 – £50,270 | C49: 0.0875
A50: Higher Rate | B50: £50,271 – £125,140 | C50: 0.3375
A51: Additional Rate | B51: Over £125,140 | C51: 0.3935
A53: Note: You pay dividend tax based on where your total income places you in the income tax bands. The first £500 of dividend income is tax-free for all taxpayers.
A55: Calculate the same way as normal income, just different allowances and bands
A57: Savings Income Rates - Applies to all UK
A60: Tax Band | B60: Savings Allowance | C60: Savings Tax Rate
A61: Basic Rate Taxpayer | B61: 1000 | C61: 0.2
A62: Higher Rate Taxpayer | B62: 500 | C62: 0.4
A63: Additional Rate Taxpayer | B63: 0 | C63: 0.45
A66: Note: You may also qualify for the Starting Rate for Savings (0%) on up to £5,000 of savings interest if your total earned income is below approximately £17,570.
A67: Savings income includes interest from bank accounts, building societies, government bonds, and corporate bonds.
A69: Calculate the same way as normal income, just different allowances and bands
A71: Capital Gains Rates - Applies to all UK
A73: Asset Type | B73: Basic Rate Taxpayer | C73: Higher/Additional Rate Taxpayer
A74: Shares, crypto, general assets | B74: 0.1 | C74: 0.2
A75: Residential property | B75: 0.18 | C75: 0.24
A77: 4. How It Works
A78: 1. Add up all your gains from selling assets in the year.
A79: 2. Subtract your CGT allowance (£3,000).
A80: 3. Add your remaining gains to your total income to work out your tax band.
A81: 4. Pay 10% or 18% on gains in the basic rate band.
A82: 5. Pay 20% or 24% on gains above that.
A85: Example 1
A86: You earn £30,000 and original cost is £20,000 and make a £10,000 capital gain (not property) - (ALWAYS Prompt this if income received way out of range specified, if user specifies a sale of asset, ask them for document proving original cost - For HMRC purposes. If not they can just specify amount.
A87: - Subtract £3,000 allowance → £7,000 taxable gain
A88: - Income + gain = £37,000 → all in basic rate
A89: - CGT = 10% × £7,000 = £700
A92: Example 2 - Standard Relief
... A103: Example 3: Business Asset Rollover Relief Applied
E104: Prompt:
A105: • Asset Sold: Shop premises (used in a sole trader business) | E105: If an unusual amount has come in to the bank, we can ask the user what this is for. If this is for the sale of a business asset used, we ask the owner if they are looking to buy a new one (of the same item)
A106: • Sale Proceeds: £200,000
A107: • Original Purchase Cost: £120,000
A108: • Capital Gain: £80,000
A109: • Amount Reinvested in new business premises: £150,000
A110: • Amount not reinvested: £50,000 (200,000 – 150,000)
A111: • Chargeable Gain Now: £50,000
A112: • Deferred Gain: £80,000 – £50,000 = £30,000
A113: • New Asset Cost: £150,000 – £30,000 = £120,000 (base cost for future CGT)
A115: So the relief reduces the chargeable gain, and then in the futre reduces the cost of the asset, which means nil effect and relief for this year until the asset is sold.
A118: National Insurance - Applies to all UK
A120: - Class 2: Flat rate £3.45/week if profits are £6,725 or more. | E120: AI Prompt: IB will calculate if total NI (Class 1 employee + Class 4 Self Employed) exceeds annual limit.
A121: - Class 4: Based on profits ONLY FROM SELF EMPLOYED/Sole trader | E121: If total NI is more than £6k, prompt user that they may be eligible for a refund and must check with HMRC on paying too much NI.
E122: "You may be eligible for a refund of Class 4 National Insurance if your total NI contributions exceed the HMRC limit. Submit Form CA5610 after your tax return to request a review."
A123: Profit Band | B123: Annual Equivalent | C123: Rate (Class 4)
A124: Below £12,570 | B124: £0 – £12,570 | C124: 0 | E124: We do not send this amount to HMRC, they will calculate themselves. But for the sake of the daily tax liability we need to calculate in the bank end
A125: Main Rate | B125: £12,571 – £50,270 | C125: 0.06
A126: Additional Rate | B126: Above £50,270 | C126: 0.02
A128: 4. Example – Sole Trader with £30,000 Profit
A129: • Class 2 = £3.45 × 52 = £179.40
A130: • Class 4:
A131: - First £12,570 = 0%
A132: - £30,000 − £12,570 = £17,430 at 6% = £1,045.80
A133: • Total NI = £179.40 + £1,045.80 = £1,225.20
A135: Gift Aid
A137: Donation gross up by 25% then deduct from income (IF on the Charity approved list) SEE LIST OF popular charities in the UK
A138: "Did you tick the gift aid box when making this donation?" | C138: << IF Yes allowable, if not ticked then do not include this donation in calculations - Do not add back to income either as its not disallowable.
A140: EXAMPLE: | F140: API Name: | G140: giftAidPayments. totalAmount
A141: Donation in the year was £1,000
A142: Gross up of £1k : | B142: =1000*1.25 -> 1250
A144: Deduct £1,250 from total taxable income
A145: Then increase TAX bands by this grossed up amount (Income tax/Savings and Dividend tax bands ONLY)
...

Sheet Student Loan
A1: STUDENT LOANS RULES
A2: 📌 Who Has to Pay? A user must repay student loans through Self Assessment if they: - Have income above the repayment threshold (Intellibooks will check if employment income is above the thresholds if this is pulled from HMRC's API) - Have an outstanding loan with the Student Loans Company (SLC) IntelliBooks should ask: “Do you have a student loan?” with options: - Plan 1 - Plan 2 - Plan 4 - Postgraduate Loan - No I dont 💰 How Repayment Works Loan Types and Thresholds (2025/26 estimates): - Plan 1: £24,990 at 9% - Plan 2: £27,295 at 9% - Plan 4 (Scotland): £31,395 at 9% - Postgraduate Loan: £21,000 at 6% Repayments apply to income above the respective thresholds. ✅ IntelliBooks Calculation Logic Example: Income = £42,000, Plan 2 Repayment = (42,000 - 27,295) × 9% = £1,569.45 Postgraduate Loan (if applicable): Repayment = (42,000 - 21,000) × 6% = £1,860 IB should calculate both and display separately. 📤 What to Submit to HMRC (API) You do not submit repayment amounts. You only submit the plan flags: - Student Loan Plan - Postgrad Loan
A14: API Example: | J14: API Name:
A16: "studentLoanAndPostgraduateLoan": { | J16: Student Loan Plan Type | N16: studentLoan.planType
A17: "studentLoan": { | J17: Student Loan Postgrad Loan flag | N17: studentLoan.postgradLoan
A18: "planType": "plan2"
A19: },
A20: "postgraduateLoan": {
A21: "repayment": true
A22: }

Sheet Steps for Calculation
A1: Personal Allowance tapering (step 2 calculation) | G1: For tax calculations (IB platform)
A2: 1) | B2: Calculate total income for the year (All income BUT Capital gains) | G2: 1) | H2: Take all Taxable Income (Capital gains/savings income/dividends are banded together separately as they have different rates)
A3: 2) | B3: If under 100k then use full £12,570 allowance | G3: 2) | H3: Check if total taxable income is over 100k (PA tapering check)
A4: 3) | B4: If Adjusted Net Income (total taxable income less pension and gift aid) over 100k then the following applies: | G4: 3) | H4: If loss, apply loss reliefs (if income is left after loss deducted, the allowances can be applied, if not then do not apply)
A5: 3.1) | B5: Adjusted Net Income (ANI) less £100k divided by 2 | G5: 4) | H5: If savings income check personal savings allowance (PSA) and Starting rate of £5k allowance (if under PA allowance)
A6: 3.2) | B6: Take that amount an deduct from PA of £12,570 | G6: 5) | H6: If dividend income apply automating allowance of £500
A7: 3.3) | B7: If total ANI >= £125,140 then PA is fully removed | G7: 6) | H7: Deduct Allowable Expenses
A8: 4) | B8: Now apply this amount as the new personal allowance and deduct from ANI | G8: 7) | H8: Add back Disallowable Expenses
G9: 8) | H9: Apply Capital Allowances (if user has agreed to this tax saving and has an asset in the pool that can be claimed)
G10: 9) | H10: Apply Trading Allowance if expenses and lower than £1,000
G11: 10) | H11: If Property income has been chosen and the allowable property expenses is less than £1,000, then apply this. Or if no expenses, then apply this.
G12: 11) | H12: If Capital gains income, apply CGT £3,000 allowance. Also apply reliefs (Business Asset rollover relief on next page)
G13: 12) | H13: Then Apply Personal allowance (Personal allowance calculation below with examples)
G14: 13) | H14: Then apply pension (if UK approved) gross up
G15: 14) | H15: Then apply gift aid calculation gross up if eligible
G16: 15) | H16: Then Apply trading income to income bands (Calculation on next page)
G17: 16) | H17: Then Apply savings income to savings income bands (Calculation on next page, IF THIS INCOME HAS BEEN CHOSEN)
G18: 17) | H18: Then Apply dividends income to dividend income bands (Calculation on next page, IF THIS INCOME HAS BEEN CHOSEN)
G19: 18) | H19: Then Apply capital gains income to percentage (Calculation on next page, IF THIS INCOME HAS BEEN CHOSEN)
G20: 19) | H20: Apply tax already deducted if also employed PAYE or CIS (Detected through HMRC API)
G21: 20) | H21: Apply NI class 2 and class 4
A22: Everything here needs to be calculated so use relevant rules - We need to do this so the user knows how much to put away per month. | G22: 21) | H22: Apply Student Loan to pay (look at student loan tab for calculation)
G23: 22) | H23: If self assessment plus NI is >1k - then POA (check Rates for tax calculation tab for how to calculate)
G25: Everything here needs to be calculated so use relevant rules - We need to do this so the user knows how much to put away per month.
G30: For tax return (HMRC)
G31: 1) | H31: Take all Taxable Income (Capital gains/savings income/dividends are banded together separately as they have different rates)
G32: 2) | H32: If loss, apply loss reliefs (if income is left after loss deducted, the allowances can be applied, if not then do not apply)
G33: 3) | H33: Send amounts for allowable expenses
G34: 4) | H34: Send amounts for disallowable expenses
G35: 5) | H35: Apply Capital Allowances (if user has agreed to this tax saving and has an asset in the pool that can be claimed)
G36: 6) | H36: Apply Trading Allowance if expenses and lower than £1,000
G37: 7) | H37: If Property income has been chosen and the allowable property expenses is less than £1,000, then apply this. Or if no expenses, then apply this.
G38: 8) | H38: If Capital gains income, apply CGT income only. Also apply reliefs if eligible
G39: 9) | H39: Then apply pension (if UK approved) gross up and send
G40: 10) | H40: Then apply gift aid calculation gross up if eligible - gross up and send
G41: 11) | H41: Apply tax already deducted if also employed PAYE or CIS (Detected through HMRC API)
G42: 12) | H42: Apply NI Calculations
G43: 13) | H43: Send HMRC Student loan plan type if eligible and specified by user upon setup
G50: This is how we would send to HMRC

Sheet Daily Tax Calculation method
A1: Daily Tax Calculation Method – IntelliBooks (Sole Trader)
A2: Purpose: give a clear, automatable method to (1) compute an up‑to‑date daily tax liability, (2) check if current cash is enough to cover upcoming tax deadlines, and (3) recommend a monthly set‑aside amount. This aligns with your Rules & Logic under SOLE TRADER and HMRC submission flow.
A3: 1) Data Inputs & Sources (auto‑collected)
A4: • Bank feeds (Open Banking): categorised cash in/out; CIS receipts; recurring patterns.
A5: • User profile: jurisdiction (Scotland vs rUK), marital status, student loan plan, CIS registration, pension/gift aid flags.
A6: • Income modules: self‑employment (turnover, allowable/disallowable, capital allowances), UK property (FHL/non‑FHL), dividends, savings, capital gains.
A7: • Losses: brought‑forward pools (via MTD losses API if available) and current‑year loss choices (same‑year/carry‑back/carry‑forward).
A8: • Adjustments: pensions (relief‑at‑source gross up), Gift Aid (gross up), trading/property allowances, rent‑a‑room, mortgage interest rules, PSA/starting rate, dividend allowance.
A9: • HMRC feeds (where available): PAYE employment income/tax deducted, CIS deducted at source, student loan flags, prior‑year liability for Payments on Account logic.
A10: • Config (per tax year): income tax bands (rUK/Scotland), dividend/savings/CGT allowances, NI Class 2/4 thresholds and rates.
A11: 2) High‑Level Algorithm (daily run)
A12: • A. Build YTD ledgers by source: self‑employment profit, property profit, dividends, savings, employment PAYE, CGT, other.
... A139: • What changed since yesterday: deltas from new transactions, category changes, gift aid/pension updates.

Sheet Daily TaxBot Cal Examples
A1: Daily Tax – rUK vs Scotland Worked Examples (IntelliBooks, Sole Trader)
A2: Two parallel, step-by-step examples using the same income profile. The only difference is the non‑savings income tax bands: rUK vs Scotland. Everything else (savings/dividends rules, PAYE credits, NI, buffer logic) is identical.
A3: Common Context & Timing
A4: Today: 1 Oct | Next deadline: 31 Jan | Days since 6 Apr: ~178 | Days to deadline: 122 | Months remaining: 5
A5: Assumptions shared by both examples: no Gift Aid or Pension relief; no student loan; no losses; no POA this year.
A6: Step 1 – YTD & Annualisation Factor (AF)
A7: YTD inputs (from Open Banking/HMRC):
A8: • Self‑employment profit YTD: £19,500 (turnover − allowable expenses − capital allowances)
A9: • PAYE salary YTD: £18,000; PAYE tax deducted YTD: £2,100
A10: • Savings interest YTD: £300 | Dividends YTD: £600
A11: AF (safe annualise): AF = 365 / 178 ≈ 2.05 (clamped ≤ 2.5)
A12: Step 2 – Project to Year‑End (per source)
... A54: Next deadline: 31 Jan

Sheet B
A1: TAXABLE INCOME TYPES AND ALLOWANCES FOR EACH

Sheet Income Type to Tax Form
A1: Income Type | B1: Sub-Income Category Type (Trigger) | C1: API Section | D1: API Field Name | E1: Allowances Trigger | F1: AI Flag: | G1: Rule for IB | H1: GL Name (Breakdown) | I1: Financial Statement | J1: Heading | K1: Notes
A2: Dividend Income | B2: N/A | C2: dividendsIncome | D2: dividendsIncome.ukDividends | E2: First £500 of dividend income is allowable. Total foreign and UK dividend and then deduct £500 allowance. - HMRC automatically applies and we calculate ourselves for estimated tax | F2: If user specifies this as their income type, and gives monthly range, the AI ML should recognise this and categorise this in the GL as "Dividend Income" | G2: Using Fuzzy Matching, check if amounts match what user specified for dividend income upon setup. If this is the users only income, then automatically assing to this GL Code. | H2: UK Dividend Income | I2: Income Statement | J2: Turnover | K2: Included for Tax
A3: Savings Income | B3: N/A | C3: savingsAndGainsIncome | D3: savingsAndGainsIncome.bankInterest | E3: Personal Savings Allowance/Savings Allowance - HMRC automatically applies and we calculate ourselves | F3: If user specifies this as their income type, and gives monthly range, the AI ML should recognise this and categorise this in the GL as "Savings Income" | G3: Since this mainly comes from financial instituitions, we use the MCC Code as a fall back if this income is specified all MCC Codes, 6000-6999. - Or use merchant name to see if this is interest from a financial instituition. We only use these two IF user has specified more than one income type that includes savings income. However, the rang specified should aid AI ML i making decision on type of income. | H3: UK Savings Income | I3: Income Statement | J3: Turnover | K3: Included for Tax
A4: Employment Income | B4: N/A | C4: employment | D4: employment.income | E4: pulled in from HMRC API | F4: pulled in from HMRC API | G4: Apply to API return, when IF HMRC give employment information. Use tax deducted as relief to recalculate estimated tax owed for the sake of user vision. | H4: N/A | I4: N/A | J4: N/A | K4: Only for Tax calculations not P+L as this is personal income not sales
A5: Self Employment Income (Trading Income) | B5: N/A | C5: selfemployment | D5: selfEmployment.income.turnover | E5: Trading Allowances/Capital Allowances/Use of Home as Office/Loss Relief/Pension Relief | F5: If user specifies this as their income type, and gives monthly range, the AI ML should recognise this and categorise this in the GL as "SE Income" - Also if Invoices are sent and managed through IB, this should be also recognised this way by matching amounts to invoices. | G5: If VAT, ensure to take NET amount only as turnover. | H5: UK Self Employment Income | I5: Income Statement | J5: Turnover | K5: Included for Tax
A6: Trust Income | B6: N/A | C6: trustAndEstates | D6: trustAndEstates.amount | E6: Tax deducted at source can be claimed. | F6: User would have specified if this income is received | G6: Ask user to upload documentation for tax deducted at source "taxpaid" | H6: UK Trust Income | I6: Income Statement | J6: Turnover | K6: Included for Tax
A7: Capital Gains Income | B7: N/A | C7: capitalGains | D7: capitalgains.totalGains | E7: Loss Relief/Annual Exempt Amount/Rollover Relief/Gift Holdover Relief | F7: User specifies this/ Or if unknown amount hits the bank, we notify user for confirmation if amount is out of range specified upon setup./Using Fuzzy Matching to see clues in description e.g "Sale of Car", "Sale of Asset". E.g if sale of car, check if money in from MCC Code belonging to Automotive dealers | G7: Ask user for this, if not already specified. | H7: UK Capital Gains Income | I7: Income Statement | J7: Turnover | K7: Included for Tax
A8: Foreign Income | B8: Dividend Income (Foreign) | C8: foreignIncome | D8: foreignIncome.foreignDividends | E8: First £500 of dividend income is allowable. Total foreign and UK dividend and then deduct £500 allowance/ FTCR | F8: If user specifies this income type and if amount falls withing specified range. (Trigger Remittance basis rules) | G8: Ask user to upload documentation for foreign tax deducted at source "taxpaid" | H8: Dividend Income (Foreign) | I8: Income Statement | J8: Turnover | K8: Included for Tax
A9: Foreign Income | B9: Savings Income (Foreign) | C9: foreignIncome | D9: foreignIncome.foreignInterest | E9: Personal Savings Allowance/Savings Allowance - Total with UK Savings income then deduct./FTCR | F9: If user specifies this income type and if amount falls withing specified range. (Trigger Remittance basis rules) | G9: Ask user to upload documentation for foreign tax deducted at source "taxpaid" | H9: Savings Income (Foreign) | I9: Income Statement | J9: Turnover | K9: Included for Tax
A10: Foreign Income | B10: Furnished Holiday Let (EEA Property) | C10: foreignIncome | D10: foreignIncome.eeaFhlProperty | E10: Capital Allowances/ Mortgage Interest/Pension Contributions/Rollover Relief/FTCR | F10: If user has specified this type of foreign income, Ask user for address of the property. Also detected on bank feeds, i.e from accomodation and hospitality websites such as AirBNB or Booking.com - Address of this property needs to be entered to see country and to ensure not main residence. (Trigger Remittance basis rules) | G10: Ask user to upload documentation for foreign tax deducted at source "taxpaid" | H10: Furnished Holiday Let (EEA Property) | I10: Income Statement | J10: Turnover | K10: Included for Tax
A11: Foreign Income | B11: Furnished Holiday Let (Outside UK and EEA) | C11: foreignIncome | D11: foreignIncome.foreignPropertyIncome | E11: FTCR | F11: If user has specified this type of foreign income, Ask user for address of the property. Also detected on bank feeds, i.e from accomodation and hospitality websites such as AirBNB or Booking.com - Address of this property needs to be entered to see country and to ensure not main residence. (Trigger Remittance basis rules) | G11: Ask user to upload documentation for foreign tax deducted at source "taxpaid" | H11: Furnished Holiday Let (Outside UK and EEA) | I11: Income Statement | J11: Turnover | K11: Included for Tax
A12: Foreign Income | B12: Residential Rental Income | C12: foreignIncome | D12: foreignIncome.foreignPropertyIncome | E12: FCTR/Full Mortgage Interest deduction/Letting Agent Fee/Insurance/Utilities paid by landlord/Property Management Fees | F12: If user specifies this income type and if amount falls withing specified range. (Trigger Remittance basis rules) | G12: Ask user to upload documentation for foreign tax deducted at source "taxpaid" | H12: Residential Rental Income (Foreign) | I12: Income Statement | J12: Turnover | K12: Included for Tax
... A19: UK Property Income | B19: Commerical Rental Income | C19: ukProperty | D19: ukProperty.ukNonFhlProperty | E19: Property Allowance/Capital Allowance/Finance Costs deduction | F19: If user specifies this income type and if amount falls withing specified range. | G19: <<<<<<<<<<<<<<<<<<<<<<<<<<<<<<<<<<<<<<<<<<<<< | H19: Commerical Rental Income (UK) | I19: Income Statement | J19: Turnover | K19: Included for Tax

Sheet Allowances 
D1: £ | G1: £
A2: Income Type | B2: Allowance | C2: API Name | D2: Amount | E2: Trigger When: | F2: Prompt: | G2: Calculation | H2: AI Flag: | I2: Will IB calculate this:
A3: Dividend Income | B3: Dividend Allowance | C3: HMRC Automatically applies this | D3: 500 | E3: When user picks dividends income as an income type upon setup. | F3: None | G3: Always apply full amount , no rules. | H3: If user picks dividend allowance, automatically apply £500 as an allowance. | I3: Yes for estimated tax amounts
A4: Savings Income | B4: Personal Savings Allowance | C4: HMRC Automatically applies this | D4: Basic Rate - £1,000/Higher Rate - £500/Advanced - 0 | E4: if total income for the year is less that 12,570 | F4: None | G4: Base allowance on main income type taxpayer rate if there is other income (ie employment income/self employment income) - If not then use savings rate income band (wherever it falls based on annual savings income) - Same for scotland | H4: If user picks savings allowance as an income type, automatically apply for internal calculations. If Main income type then apply then we see total cumulative net income and what band it falls in. But if secondary or tertiary, look at main income and where the net income type falls in what band. | I4: Yes for estimated tax amounts
B5: Savings Allowance - Starting Rate | C5: HMRC Automatically applies this | D5: 5000 | E5: When user picks savings income as an income type upon setup. | F5: If amount out of range specified, IB should ask the user what this income relates to. The IB will know supplier name, and match through fuzzy matching. | G5: Only available if total income is below the personal allowance threshold. Remove this allowance if annual cumulative total income over >17,570 | H5: If user picks savings allowance as an income type, automatically apply this UNTIL total net income is over the 12,570 threshold. | I5: Yes for estimated tax amounts
A6: Self Employment Income (Trading Income) | B6: Trading Allowances | C6: selfEmployment.tradingAllowance | D6: 1000 | E6: If self employment income is selected, then apply this automatically, until allowable expenses surpasses £1,000. Once this happens use allowable expense instead. | F6: If total allowable expenses under £1,000 for the year, then automatically apply. | G6: Deduct the 1,000 from the turnover, if rule applies. | H6: Deduct the 1,000 from the turnover, if rule applies. | I6: Yes for the API and Test. Tax calc. (If expenses for the year are under <1,000, we ask upon submission: "Do you want to claim the £1,000 trading allowance instead of entering expenses" - and tell them why and the benefit.
B7: Capital Allowances | C7: selfEmployment.capitalAllowances | D7: >=£500 | E7: If >£500 in category of service and auto parts as well as electronics and software, and home | F7: "Is this an item you will use for more than a short period?" | G7: Check CAPITAL ALLOWANCES Tab | H7: If met then apply capital allowances rules shown in the "Capital Allowances tab" | I7: Yes
B8: Use of Home as Office Allowance | C8: otherExpenses | D8: check calculation. | E8: Business address and Home Address are the same | F8: Ask user how many rooms in their property, and how many are used for business. (Total of Rent/mortgage Interest, Utilities, Internet, Council Tax, Home Insurance) | G8: No of rooms used/total rooms in house times cost. | H8: End of the first month of setup, ask the user if any home bills are paid - ONLY DO THIS IF BOTH ADDRESSES ARE THE SAME
B9: Loss Relief | C9: Check Tab | D9: Check Tab | E9: Check Tab | F9: Check Tab | G9: Check Tab | H9: Check Tab | I9: Check Tab
B10: Pension Reliefs | C10: pension.Contributions.totalPaymentsIntoRAS | D10: total amount paid in the year | E10: fuzzy matching shows amount paid into pension - Get AI ML to fuzzy match to list of registered UK pension providers. If on this list then assume relief, and if this income is chosen. | G10: total in paid to registered UK pension provider - pension paid in bank times by 100 divided by 80 always. | H10: Total contribution calculated is allowable | I10: Yes for estimated tax amounts, but total amount for pension calculated will be sent.
A11: Trust Income | B11: Tax Deducted at source | C11: taxTakenOff | D11: Amount that they receive is applied and put on the API. | E11: When user picks trust income as an income type upon setup. | F11: Ask user to upload document for tax taken off at source if possible. So we can see actual net income. | G11: Add the tax taken at source plus the amount received in the bank. | H11: Ensure that tax document or evidence of tax at source is uploaded upon detection of income. | I11: Yes for estimated tax amounts, and will be sent over to HMRC
A12: Capital Gains Income | B12: Loss Relief | C12: Check Tab | D12: Check Tab | E12: Check Tab | F12: Check Tab | G12: Check Tab | H12: Check Tab | I12: Check Tab
B13: Annual Exempt Amount | C13: capitalGains.annualExemptAmountUsed | D13: 3000 | E13: When user picks capital gains income as an income type upon setup. | F13: automatically applied | G13: deduct this from the net gains | H13: <<<<<<<<<<<<<<<<<<<<<<<<<<<,, | I13: Yes for estimated tax amounts, and will be sent over to HMRC
B14: Rollover Relief | C14: capitalGains.businessAssetRolloverRelief | D14: Unlimited - up to full gain can be deferred. | E14: Sale of a qualifying business asset and the proceeds are reinvested into another qualifying business asset within 3 years before or after. | F14: "Have you reinvested the proceeds of a business asset sale into another asset? If so what date (and this brings all the transactions on that date and they choose the transaction this relates to) " | G14: So the relief reduces the chargeable gain, and then in the future reduces the cost of the asset, which means nil effect and relief for this year until the asset is sold. | H14: If asset sold and bought are bought qualifying assets then relief can be applied. If gain> reinvested amount -> Defer up to reinvested amount, and tax difference now. -> Reduce new asset base cost by deferred portion only. | I14: Yes for estimated tax amounts, and will be sent over to HMRC (Gain amount, relief amount claimed, adjusted base cost of the new asset.)
A15: Dividend Income (Foreign Income) | B15: Dividend Allowance | C15: HMRC Automatically applies this | D15: 500 | E15: When user picks dividends income as an income type upon setup. | G15: Always apply full amount , no rules. | H15: If user picks dividend allowance, automatically apply £500 as an allowance. | I15: Yes for estimated tax amounts
B16: Foreign Credit Tax Relief | C16: foreignIncome.foreignTaxPaid | D16: Capped at UK TAX DUE | E16: User has specified Foreign dividend income upon setup. And amount hits the bank. | F16: Ask user to upload documentation on tax paid abroad if applicable | G16: When user specifies foreign tax, IB should compare UK translated foregin tax to UK tax. Always cap at UK tax due. If Foreign<UK then Tax payable. If Foreign>UK, then no extra tax payable. | H16: <<<<<<<<<<<<<<<<<<<<<<<<<<<,, | I16: Yes for estimated tax amounts, and will be sent over to HMRC (Gain amount, relief amount claimed, adjusted base cost of the new asset.)
B17: Remittance Basis Relief | C17: remittanceBasis | D17: either true or false if presence score is high | E17: Domicile Detection | F17: "Your data suggests a strong UK or foreign footprint. We recommend reviewing your domicile/residency status before claiming remittance basis" | I17: Developer to look at "Domicile risk" in background - We will create a presence score.
A18: Savings Income (Foreign Income) | B18: Personal Savings Allowance | C18: HMRC Automatically applies this | D18: Basic Rate - £1,000/Higher Rate - £500/Advanced - 0 | F18: None | G18: Base allowance on main income type taxpayer rate if there is other income (ie employment income/self employment income) - If not then use savings rate income band (wherever it falls based on annual savings income) - Same for scotland | H18: If user picks savings allowance as an income type, automatically apply for internal calculations. If Main income type then apply then we see total cumulative net income and what band it falls in. But if secondary or tertiary, look at main income and where the net income type falls in what band. | I18: Yes for estimated tax amounts
B19: Savings Allowance - Starting Rate | C19: HMRC Automatically applies this | D19: 5000 | E19: When user picks savings income as an income type upon setup. | F19: If amount out of range specified, IB should ask the user what this income relates to. The IB will know supplier name, and match through fuzzy matching. | G19: Only available if total income is below the personal allowance threshold. Remove this allowance if annual cumulative total income over >17,570 | H19: If user picks savings allowance as an income type, automatically apply this UNTIL total net income is over the 12,570 threshold. | I19: Yes for estimated tax amounts
B20: Foreign Credit Tax Relief | C20: foreignIncome.foreignTaxPaid | D20: Capped at UK TAX DUE | E20: User has specified Foreign savings income upon setup. And amount hits the bank. | F20: Ask user to upload documentation on tax paid abroad if applicable | G20: When user specifies foreign tax, IB should compare UK translated foregin tax to UK tax. Always cap at UK tax due. If Foreign<UK then Tax payable. If Foreign>UK, then no extra tax payable. | H20: <<<<<<<<<<<<<<<<<<<< | I20: Yes for estimated tax amounts, and will be sent over to HMRC (Gain amount, relief amount claimed, adjusted base cost of the new asset.)
B21: Remittance Basis Relief | C21: remittanceBasis | D21: either true or false if presence score is high | E21: Domicile Detection | F21: "Your data suggests a strong UK or foreign footprint. We recommend reviewing your domicile/residency status before claiming remittance basis" | I21: Developer to look at "Domicile risk" in background - We will create a presence score.
A22: Furnished Holiday Let (EEA Property) (Foreign Income) | B22: Capital Allowances | C22: selfEmployment.capitalAllowances | D22: >=£500 | E22: If >£500 in category of service and auto parts as well as electronics and software, and home | F22: "Is this an item you will use for more than a short period?" | G22: Check CAPITAL ALLOWANCES Tab | H22: If met then apply capital allowances rules shown in the "Capital Allowances tab" | I22: Yes
B23: Mortgage Interest | C23: financeCosts | D23: whatever is shown in GL | E23: Sub-Income category shown is picked. | F23: "You may be eligible for mortgage interest relief, since your income is an FHL, Can I have a breakdown of the mortgage interest on these payments? These are 100% deductible and will save you tax!" Then also give user as option to ask where they can get this information - "If you do not have this on your Lnder's online portal, please ask them for a copy of this document. We would also need to retain this for HMRC" | G23: Is an allowable expense, deduct 100% of cost | H23: <<<<<<<<<<<<<<<<<<<< | I23: Yes for estimated tax amounts, and will be sent over to HMRC (Gain amount, relief amount claimed, adjusted base cost of the new asset.)
B24: Pension Reliefs | C24: totalPaymentsIntoRAS | D24: total amount paid in the year | E24: fuzzy matching shows amount paid into pension - Get AI ML to fuzzy match to list of registered UK pension providers. If on this list then assume relief, and if this income is chosen. | G24: total in paid to registered UK pension provider - pension paid in bank times by 100 divided by 80 always. Then also increase tax bands by this amount | H24: Total contribution calculated is allowable | I24: Yes for estimated tax amounts, but total amount for pension calculated will be sent.
B25: Foreign Credit Tax Relief | C25: foreignIncome.foreignTaxPaid | D25: Capped at UK TAX DUE | E25: User has specified Foreign savings income upon setup. And amount hits the bank. | F25: Ask user to upload documentation on tax paid abroad if applicable | G25: When user specifies foreign tax, IB should compare UK translated foregin tax to UK tax. Always cap at UK tax due. If Foreign<UK then Tax payable. If Foreign>UK, then no extra tax payable. | H25: <<<<<<<<<<<<<<<<<<<< | I25: Yes for estimated tax amounts, and will be sent over to HMRC (Gain amount, relief amount claimed, adjusted base cost of the new asset.)
B26: Remittance Basis Relief | C26: remittanceBasis | D26: either true or false if presence score is high | E26: Domicile Detection | F26: "Your data suggests a strong UK or foreign footprint. We recommend reviewing your domicile/residency status before claiming remittance basis" | I26: Developer to look at "Domicile risk" in background - We will create a presence score.
A27: Furnished Holiday Let (Outside UK and EEA) (Foreign Income) | B27: Foreign Credit Tax Relief | C27: foreignIncome.foreignTaxPaid | D27: Capped at UK TAX DUE | E27: User has specified Foreign savings income upon setup. And amount hits the bank. | F27: Ask user to upload documentation on tax paid abroad if applicable | G27: When user specifies foreign tax, IB should compare UK translated foregin tax to UK tax. Always cap at UK tax due. If Foreign<UK then Tax payable. If Foreign>UK, then no extra tax payable. | H27: <<<<<<<<<<<<<<<<<<<< | I27: Yes for estimated tax amounts, and will be sent over to HMRC (Gain amount, relief amount claimed, adjusted base cost of the new asset.)
B28: Remittance Basis Relief | C28: remittanceBasis | D28: either true or false if presence score is high | E28: Domicile Detection | F28: "Your data suggests a strong UK or foreign footprint. We recommend reviewing your domicile/residency status before claiming remittance basis" | I28: Developer to look at "Domicile risk" in background - We will create a presence score.
A29: Residential Rental Income (Foreign Income) | B29: Foreign Credit Tax Relief | C29: foreignIncome.foreignTaxPaid | D29: Capped at UK TAX DUE | E29: User has specified Foreign property income for residential properties upon setup. And amount hits the bank. | F29: Ask user to upload documentation on tax paid abroad if applicable | G29: When user specifies foreign tax, IB should compare UK translated foregin tax to UK tax. Always cap at UK tax due. If Foreign<UK then Tax payable. If Foreign>UK, then no extra tax payable. | H29: <<<<<<<<<<<<<<<<<<<< | I29: Yes for estimated tax amounts, and will be sent over to HMRC (Gain amount, relief amount claimed, adjusted base cost of the new asset.)
B30: Partial Mortgage Interest deduction | C30: financeCosts | D30: whatever is shown in GL | E30: Sub-Income category shown is picked. | F30: "You may be eligible for mortgage interest relief, since your income is an FHL, Can I have a breakdown of the mortgage interest on these payments? These are 100% deductible and will save you tax!" Then also give user as option to ask where they can get this information - "If you do not have this on your Lnder's online portal, please ask them for a copy of this document. We would also need to retain this for HMRC" | G30: Is an allowable expense, deduct 20% of cost | H30: <<<<<<<<<<<<<<<<<<<< | I30: Yes for estimated tax amounts, and will be sent over to HMRC (Gain amount, relief amount claimed, adjusted base cost of the new asset.)
B31: Remittance Basis Relief | C31: remittanceBasis | D31: either true or false if presence score is high | E31: Domicile Detection | F31: "Your data suggests a strong UK or foreign footprint. We recommend reviewing your domicile/residency status before claiming remittance basis" | I31: Developer to look at "Domicile risk" in background - We will create a presence score.
A32: Commerical Rental Income (Foreign Income) | B32: Foreign Credit Tax Relief | C32: foreignIncome.foreignTaxPaid | D32: Capped at UK TAX DUE | E32: User has specified Foreign property income for residential properties upon setup. And amount hits the bank. | F32: Ask user to upload documentation on tax paid abroad if applicable | G32: When user specifies foreign tax, IB should compare UK translated foregin tax to UK tax. Always cap at UK tax due. If Foreign<UK then Tax payable. If Foreign>UK, then no extra tax payable. | H32: <<<<<<<<<<<<<<<<<<<< | I32: Yes for estimated tax amounts, and will be sent over to HMRC (Gain amount, relief amount claimed, adjusted base cost of the new asset.)
B33: Remittance Basis Relief | C33: foreignIncome.remittanceBasis | D33: either true or false if presence score is high | E33: Domicile Detection | F33: "Your data suggests a strong UK or foreign footprint. We recommend reviewing your domicile/residency status before claiming remittance basis" | I33: Developer to look at "Domicile risk" in background - We will create a presence score.
A34: Capital Gains (Foreign Income) | B34: Foreign Credit Tax Relief | C34: foreignIncome.foreignTaxPaid | D34: Capped at UK TAX DUE | E34: User has specified Foreign property income for residential properties upon setup. And amount hits the bank. | F34: Ask user to upload documentation on tax paid abroad if applicable | G34: When user specifies foreign tax, IB should compare UK translated foregin tax to UK tax. Always cap at UK tax due. If Foreign<UK then Tax payable. If Foreign>UK, then no extra tax payable. | H34: <<<<<<<<<<<<<<<<<<<< | I34: Yes for estimated tax amounts, and will be sent over to HMRC (Gain amount, relief amount claimed, adjusted base cost of the new asset.)
B35: Annual Exempt Amount | C35: capital.Gains.annualExemptAmountUsed | D35: 3000 | E35: When user picks capital gains income as an income type upon setup. | F35: automatically applied | G35: deduct this from the net gains | H35: <<<<<<<<<<<<<<<<<<<< | I35: Yes for estimated tax amounts, and will be sent over to HMRC
B36: Loss Relief | C36: Check Tab | D36: Check Tab | E36: Check Tab | F36: Check Tab | G36: Check Tab | H36: Check Tab | I36: Check Tab
B37: Remittance Basis Relief | C37: remittanceBasis | D37: either true or false if presence score is high | E37: Domicile Detection | F37: "Your data suggests a strong UK or foreign footprint. We recommend reviewing your domicile/residency status before claiming remittance basis" | I37: Developer to look at "Domicile risk" in background - We will create a presence score.
A38: Employment Income (Foreign Income) | B38: Foreign Credit Tax Relief | C38: foreignIncome.foreignTaxPaid | D38: Capped at UK TAX DUE | E38: User has specified Foreign property income for residential properties upon setup. And amount hits the bank. | F38: Ask user to upload documentation on tax paid abroad if applicable | G38: When user specifies foreign tax, IB should compare UK translated foregin tax to UK tax. Always cap at UK tax due. If Foreign<UK then Tax payable. If Foreign>UK, then no extra tax payable. | H38: <<<<<<<<<<<<<<<<<<<< | I38: Yes for estimated tax amounts, and will be sent over to HMRC (Gain amount, relief amount claimed, adjusted base cost of the new asset.)
B39: Remittance Basis Relief | C39: remittanceBasis | D39: either true or false if presence score is high | E39: Domicile Detection | F39: "Your data suggests a strong UK or foreign footprint. We recommend reviewing your domicile/residency status before claiming remittance basis" | I39: Developer to look at "Domicile risk" in background - We will create a presence score.
A40: UK Property Income - Furnished Holiday Let | B40: Capital Allowances | C40: selfEmployment.capitalAllowances | D40: >=£500 | E40: If >£500 in category of service and auto parts as well as electronics and software, and home | F40: "Is this an item you will use for more than a short period?" | G40: Check CAPITAL ALLOWANCES Tab | H40: If met then apply capital allowances rules shown in the "Capital Allowances tab" | I40: Yes
B41: Mortgage Interest | C41: financeCosts | D41: 100% of costs are deductible, look at "Mortagage costs" in GL - HOWEVER ONLY INTEREST ELEMENT | E41: If payment to lender classed as mortgage cost - Only ask user at the end of the tax year. | F41: "You may be eligible for mortgage interest relief, since your income is an FHL, Can I have a breakdown of the mortgage interest on these payments? These are 100% deductible and will save you tax!" Then also give user as option to ask where they can get this information - "If you do not have this on your Lnder's online portal, please ask them for a copy of this document. We would also need to retain this for HMRC" | G41: When user uploads document OCR should calculate interest in relevant tax year. Take the amount and apply to the tax returns. | H41: At the end of the tax year and with all that has been paid, ASK THE USER TO UPLOAD ANNUAL MORTGAGE STATEMENT FOR FURTHER DEDUCTIONS ON THEIR TAX LIABILITY. | I41: Yes for estimated tax amounts, and will be sent over to HMRC
B42: Pension Contributions | C42: totalPaymentsIntoRAS | D42: total amount paid in the year | E42: fuzzy matching shows amount paid into pension - Get AI ML to fuzzy match to list of registered UK pension providers. If on this list then assume relief, and if this income is chosen. | G42: total in paid to registered UK pension provider - pension paid in bank times by 100 divided by 80 always. | H42: Total contribution calculated is allowable | I42: Yes for estimated tax amounts, but total amount for pension calculated will be sent.
A43: UK Property Income - Rent-A-Room | B43: Rent-A-Room Relief (When they pick this income, ask user if they live in the property) | C43: rentARoom ("claimed"= true or false), ("jointlyLet": true or false) | D43: £7,500 if sole owner - If 2 then £3,750 (HMRC doesn’t ask amount of people) | E43: If User picks Rent A room relief ask them on their dashboard, whether they are the sole owner if not, how many owners and if the would like to claim rent a room releif. | F43: When this income type is chosen | G43: Apply £7,500 if they say jointly let £3,750 - We deduct this from income _ IF DEDCTIBLE EXPENSES ARE MORE THEN DEDUCT THAT INSTEAD - Dedduct higher of allowable expenses and Relief. | H43: <<<<<<<<<<<<<<<<<<<< | I43: Yes for estimated tax amounts, and will be sent over to HMRC
A44: UK Property Income - Residential Rental Income | B44: Property Allowance | C44: propertyIncomeAllowance | D44: 1000 | E44: Apply if income (or one of the incomes chosen) chosen is property income (Residential property). If total allowable expenses surpass £1k mark, remove allowance and use deductible expenses instead. | F44: If Expenses is lower than £1k and income over £1k - Take this at year end | G44: Deduct £1k at the year end, If income is over £1k, and expenses lower at year end - Ask user if they want trading allowance and why they are eligible. | H44: <<<<<<<<<<<<<<<<<<<< | I44: Yes for estimated tax amounts, and will be sent over to HMRC
B45: Partial Mortgage Interest deduction | C45: residentialFinancialCost | D45: 20% of costs are deductible, Trigger if there are "Mortagage costs" in GL - HOWEVER ONLY INTEREST ELEMENT - By asking user for loan statement | E45: If payment to lender classed as mortgage cost - Only ask user at the end of the tax year. | F45: "You may be eligible for mortgage interest relief, since your income is an FHL, Can I have a breakdown of the mortgage interest on these payments? These are 100% deductible and will save you tax!" Then also give user as option to ask where they can get this information - "If you do not have this on your Lnder's online portal, please ask them for a copy of this document. We would also need to retain this for HMRC" | G45: When user uploads document OCR should calculate interest in relevant tax year. Take the amount and apply to the tax returns. | H45: At the end of the tax year and with all that has been paid, ASK THE USER TO UPLOAD ANNUAL MORTGAGE STATEMENT FOR FURTHER DEDUCTIONS ON THEIR TAX LIABILITY. | I45: Yes for estimated tax amounts, and will be sent over to HMRC
A46: UK Property Income - Commerical Rental Income | B46: Property Allowance | C46: propertyIncomeAllowance | D46: 1000 | E46: Apply if income (or one of the incomes chosen) chosen is property income. If total allowable expenses surpass £1k mark, remove allowance and use deductible expenses instead. | F46: If Expenses is lower than £1k and income over £1k - Take this at year end | G46: Deduct £1k at the year end, If income is over £1k, and expenses lower at year end - Ask user if they want trading allowance and why they are eligible. | H46: <<<<<<<<<<<<<<<<<<<< | I46: Yes for estimated tax amounts, and will be sent over to HMRC
B47: Capital Allowances | C47: selfEmployment.capitalAllowances | D47: >=£500 | E47: If >£500 in category of service and auto parts as well as electronics and software, and home | F47: "Is this an item you will use for more than a short period?" | G47: Check CAPITAL ALLOWANCES Tab | H47: If met then apply capital allowances rules shown in the "Capital Allowances tab" | I47: Yes

Sheet Other reliefs
A1: Relief / Scheme | B1: Tax Effect | C1: HMRC API Field | D1: API Section (Submission Context) | E1: User Prompt | F1: Trigger in IntelliBooks | G1: Notes | H1: Bank Transaction Clues | I1: IntelliBooks Categorisation | J1: API Section Mapping | K1: Claim at Individual Level?
A2: Enterprise Investment Scheme (EIS) | B2: 30% income tax relief on qualifying investments | C2: reliefs.eisRelief | D2: individual-reliefs | E2: We detected an investment. Was this an EIS qualifying investment? | F2: Ask: 'Did you invest under the Enterprise Investment Scheme?' | G2: Can carry back 1 year; capped at £1m ordinary, £2m KIC. | H2: Transaction ref contains 'EIS Share Issue', broker name | I2: Investment | J2: individual-reliefs → reliefs.eisRelief | K2: Yes
A3: Seed Enterprise Investment Scheme (SEIS) | B3: 50% relief on qualifying investments | C3: reliefs.seisRelief | D3: individual-reliefs | E3: We detected an investment. Was this a SEIS qualifying investment? | F3: Ask: 'Did you invest under the SEIS scheme?' | G3: Max £100k per year; can carry back. | H3: Transaction ref contains 'SEIS Subscription' | I3: Investment | J3: individual-reliefs → reliefs.seisRelief | K3: Yes
A4: Venture Capital Trust (VCT) | B4: 30% relief on new VCT subscriptions | C4: reliefs.vctSubscriptions | D4: individual-reliefs | E4: Was this a qualifying VCT investment? | F4: Ask: 'Did you subscribe to new shares in a Venture Capital Trust?' | G4: Up to £200k per year. | H4: Transaction ref: 'VCT Shares', broker statement | I4: Investment | J4: individual-reliefs → reliefs.vctSubscriptions | K4: Yes
A5: Community Investment Tax Relief (CITR) | B5: 5% of investment each year for 5 years | C5: reliefs.communityInvestment | D5: individual-reliefs | E5: Was this payment into a Community Investment scheme (CITR)? | F5: Ask: 'Did you invest in a Community Development Finance Institution?' | G5: Must have accredited CITR certificate. | H5: Merchant: Community Bank, CDFI Ltd | I5: Investment | J5: individual-reliefs → reliefs.communityInvestment | K5: Yes
A6: Qualifying Loan Interest | B6: Relief for interest paid on qualifying loans | C6: reliefs.loanInterest | D6: individual-reliefs | E6: You paid loan interest. Was this a qualifying investment loan? | F6: Ask: 'Did you pay interest on qualifying loans (e.g. to invest in a partnership)?' | G6: Includes loans for partnerships, co-ownership trusts, close companies. | H6: Ref: 'Loan Repayment HSBC', 'Interest Payment Barclays' | I6: Investment | J6: individual-reliefs → reliefs.loanInterest | K6: Yes
A7: Maintenance Payments Relief | B7: Relief for certain pre-1989 divorce settlements | C7: reliefs.maintenancePayments | D7: individual-reliefs | E7: Is this a legally required maintenance payment under pre-1989 rules? | F7: Ask: 'Did you make legally required maintenance payments?' | G7: Applies only if court order and recipient born pre-1935. | H7: Ref: 'Court Order Payment', 'CSA/Child Support' | I7: Investment | J7: individual-reliefs → reliefs.maintenancePayments | K7: Yes
A8: Deficiency Relief | B8: Relief for life assurance policy deficiencies | C8: reliefs.deficiencyRelief | D8: individual-reliefs | E8: Do you have deficiency relief to claim on life assurance policies? | F8: Ask: 'Do you have deficiency relief to claim on life assurance policies?' | G8: Rare; reduces taxable income on chargeable event gains. | H8: Ref: Life Assurance company payout / deficiency adjustment | I8: Investment | J8: individual-reliefs → reliefs.deficiencyRelief | K8: Yes

Sheet Capital Allowances
A1: Type of Capital Allowance | B1: API Name
A2: Capital Allowances | B2: selfEmployment.capitalAllowances
A3: Annual Investment Allowance (AIA) | B3: annualInvestmentAllowance
A4: Main Pool Allowance | B4: capitalAllowance.MainPool
A5: Special Rate Pool | B5: capitalAllowance.SpecialRatePool
A6: Single Asset Pool | B6: capitalAllowance.SingleAssetPool
A7: Zero Emissions Goods Vehicle Allowance (FYA) | B7: zeroEmissionsGoodsVehicleAllowance
A9: IB could prompt upon setup: | B9: In the last 5 years have you purchased a vehicle (over £500) at all?
B10: If "Yes" list types of vehicles, Give cost, and year purchased.
A12: General
A13: Asset Type | B13: AIA Eligible? | C13: If AIA Used Up → Pool | D13: Notes | E13: How to calculate?
A14: Car 0 CO₂ & Brand New | B14: No | C14: First Year Allowance | D14: Cars never qualify for AIA. If ≤50g/km CO₂ then FYA | E14: Full amount can be deducted from taxable profits
A15: Car 0 g/km CO₂ & Used | B15: No | C15: Main Pool (18%) | D15: Cars never qualify for AIA. | E15: Put full thing into main pool pot b/f balance - This is where 18% will be deducted per year.
A16: Car 1 g/km >= ≤ 50g/km CO₂ | B16: No | C16: Main Pool (18%) | D16: Cars never qualify for AIA. | E16: Put full cost into main pool pot b/f balance - This is where 18% will be deducted from taxable profits per year.
A17: Car >50g/km CO₂ | B17: No | C17: Special Rate Pool (6%) | D17: Cars never qualify for AIA. | E17: Put full cost into special rate pool pot b/f balance - This is where 6% will be deducted per year.
A18: Car (Partial Business use) | B18: No | C18: Main Pool | D18: Cars never qualify for AIA. | E18: If partial business use ALWAYS create own pool - take business percentage specified and multiply by 18%.
A19: Van 0 CO₂ & Brand New | B19: Yes | C19: First Year Allowance | D19: First Year Allowance (FYA) if electric. If brand new then FYA, if not then AIA. | E19: Full amount can be deducted from taxable profits
A20: Van 0 g/km CO₂ & Used | B20: Yes | C20: Main Pool (18%) | D20: Only goes to Main pool if AIA is all used up | E20: Put full thing into main pool pot b/f balance - This is where 18% will be deducted per year.
A21: Van 1 g/km >= ≤ 50g/km CO₂ | B21: Yes | C21: Main Pool (18%) | D21: Only goes to Main pool if AIA is all used up | E21: Put full thing into main pool pot b/f balance - This is where 18% will be deducted per year.
A22: Van >50g/km CO₂ | B22: Yes | C22: Special Rate Pool (6%) | D22: Only goes to Special pool if AIA is all used up | E22: Put full thing into special rate pool pot b/f balance - This is where 6% will be deducted per year.
A23: Van (Partial Business use) | B23: Yes | C23: Main Pool | D23: First Year Allowance (FYA) if electric. If brand new then FYA, if not then AIA. | E23: If partial business use ALWAYS create own pool - take business percentage specified and multiply by 18%.
A24: Motorcycle | B24: Yes | C24: Main Pool (18%) | D24: Always qualifies. | E24: Put full cost into main pool pot b/f balance - This is where 18% will be deducted from taxable profits per year.
... A46: Software (capitalised development costs) | B46: Yes | C46: Main Pool (18%) | D46: If capitalised, else revenue deduction. | E46: Put full cost into main pool pot b/f balance - This is where 18% will be deducted from taxable profits per year.
A50: Property Income (FHL)
A51: List of Assets | B51: AIA Eligible? | C51: If AIA Used Up → Pool | D51: Calculation for IB | E51: ONLY IF AIA OF £1M IS USED UP, IF THIS IS? THEN THE ALLOWABLE ASSETS GO INTO THE SPECIFIED POOLS <<<<<
A52: Beds | B52: Yes | C52: Main Pool (18%) | D52: Put full cost into main pool pot b/f balance - This is where 18% will be deducted from taxable profits per year.
A53: Wardrobes | B53: Yes | C53: Main Pool (18%) | D53: Put full cost into main pool pot b/f balance - This is where 18% will be deducted from taxable profits per year.
A54: Other Furniture | B54: Yes | C54: Main Pool (18%) | D54: Put full cost into main pool pot b/f balance - This is where 18% will be deducted from taxable profits per year.
A55: Cooker | B55: Yes | C55: Main Pool (18%) | D55: Put full cost into main pool pot b/f balance - This is where 18% will be deducted from taxable profits per year.
A56: Fridge | B56: Yes | C56: Main Pool (18%) | D56: Put full cost into main pool pot b/f balance - This is where 18% will be deducted from taxable profits per year.
A57: Dishwasher | B57: Yes | C57: Main Pool (18%) | D57: Put full cost into main pool pot b/f balance - This is where 18% will be deducted from taxable profits per year.
A58: Fire Alarm System | B58: Yes | C58: Main Pool (18%) | D58: Put full cost into main pool pot b/f balance - This is where 18% will be deducted from taxable profits per year.
A59: Broadband Routers | B59: Yes | C59: Main Pool (18%) | D59: Put full cost into main pool pot b/f balance - This is where 18% will be deducted from taxable profits per year.
A61: Property Income (Commercial Property)
A62: Asset Type (within commercial property) | B62: AIA Eligible? | C62: If AIA Used Up → Pool | D62: Notes
A63: Electrical systems (wiring, lighting circuits, sockets) | B63: Yes | C63: Special Rate Pool (6%) | D63: Integral feature. | E63: Put full cost into main pool pot b/f balance - This is where 6% will be deducted from taxable profits per year.
A64: Cold water systems (plumbing, pipes, tanks) | B64: Yes | C64: Special Rate Pool (6%) | D64: Integral feature. | E64: Put full cost into main pool pot b/f balance - This is where 6% will be deducted from taxable profits per year.
A65: Space and water heating systems (boilers, radiators, hot water) | B65: Yes | C65: Special Rate Pool (6%) | D65: Integral feature. | E65: Put full cost into main pool pot b/f balance - This is where 6% will be deducted from taxable profits per year.
A66: Air-conditioning and air cooling systems | B66: Yes | C66: Special Rate Pool (6%) | D66: Integral feature. | E66: Put full cost into main pool pot b/f balance - This is where 6% will be deducted from taxable profits per year.
A67: Lifts, escalators, moving walkways | B67: Yes | C67: Special Rate Pool (6%) | D67: Integral feature. | E67: Put full cost into main pool pot b/f balance - This is where 6% will be deducted from taxable profits per year.
A68: External solar shading | B68: Yes | C68: Special Rate Pool (6%) | D68: Integral feature. | E68: Put full cost into main pool pot b/f balance - This is where 6% will be deducted from taxable profits per year.
A69: Security systems (CCTV, alarms, access systems) | B69: Yes | C69: Main Pool (18%) | D69: Not integral; treated as plant. | E69: Put full cost into main pool pot b/f balance - This is where 18% will be deducted from taxable profits per year.
A70: Fire safety systems (smoke alarms, sprinklers, detectors) | B70: Yes | C70: Main Pool (18%) | D70: Treated as plant. | E70: Put full cost into main pool pot b/f balance - This is where 18% will be deducted from taxable profits per year.
A71: Loose furniture (desks, chairs, shelving, storage) | B71: Yes | C71: Main Pool (18%) | D71: If landlord provides for tenants. | E71: Put full cost into main pool pot b/f balance - This is where 18% will be deducted from taxable profits per year.
A72: Computer/IT systems installed in property | B72: Yes | C72: Main Pool (18%) | D72: Servers, routers, network cabling. | E72: Put full cost into main pool pot b/f balance - This is where 18% will be deducted from taxable profits per year.
A73: Machinery installed (e.g., workshop equipment in factory) | B73: Yes | C73: Main Pool (18%) | D73: Plant & machinery definition. | E73: Put full cost into main pool pot b/f balance - This is where 18% will be deducted from taxable profits per year.
A74: Integral solar panels (roof-mounted, permanent) | B74: Yes | C74: Special Rate Pool (6%) | D74: Renewable energy asset. | E74: Put full cost into main pool pot b/f balance - This is where 6% will be deducted from taxable profits per year.
... A78: Decorative assets (painting, wallpaper, tiling) | B78: No | C78: Not allowable | D78: Repairs may be deductible as revenue instead. | E78: N/A
A80: Emissions Rules
A81: Emissions | B81: Pool
A82: >50g/km | B82: Special Rate Pool (6%)
A83: 0 | B83: First Year Allowance (100%)
A84: 1 g/km >= ≤ 50g/km | B84: Main Pool (18%)
A85: Partial business use | B85: Put in its own pool and check emissions for rate to use above
A87: 🧾 Summary of Capital Allowance Types
A89: Allowance | B89: Rate
A90: AIA (Annual Investment Allowance) | B90: 1
A91: FYA (First Year Allowance) | B91: 1
A92: WDA – Main Pool | B92: 0.18
A93: WDA – Special Rate Pool | B93: 0.06
A94: AIA Allowance | B94: 1000000 | C94: If this is all used up, then most vehicles depending on emissions go into MP (18%)
A97: If typeApproval starts with... | B97: Then vehicleType = | C97: Then allowanceType =
A98: M1 + CO₂ > 50g/km | B98: Car | C98: SRP (6%)
A99: M1 + CO₂ = 0 | B99: Electric Car | C99: FYA (100%)
A100: M1 + CO₂ ≤ 50g/km | B100: Low-Emission Car | C100: Main Pool (18%)
A101: N1, N2, N3 | B101: Van / Truck | C101: AIA (100%)
A102: L3e, L4e, L5e | B102: Motorcycle | C102: AIA (If AIA is used up Main Pool)
A103: L6e, L7e | B103: Microcar / Quad | C103: Treated like car → SRP or FYA depending on CO₂
A104: O1–O4 | B104: Trailer | C104: AIA (100%)
A105: T | B105: Tractor | C105: AIA (100%)
A108: TypeApproval | B108: Emissions | C108: Vehicle Type | D108: Allowance: | E108: Rule for IB: | F108: Check for
A109: M1 | B109: >50g/km | C109: Car/SUV/Minivan | D109: Special Rate - 6% | E109: Put in the special rate pool of 6% allowance | F109: If business use <100%, ensure you only take business percentage and then also multiply by rate
A110: M1 | B110: 0 | C110: Car/SUV/Minivan | D110: First Year Allowance | E110: Whole amount is allowable and can be allowed under capital allowances | F110: If business use <100%, ensure you only take business percentage
A111: M1 | B111: ≤ 50g/km | C111: Car/SUV/Minivan | D111: Main Pool always | E111: Put in the main pool of 18% allowance | F111: If business use <100%, ensure you only take business percentage and then also multiply by rate
A112: M2 / M3 | B112: Depends | C112: Minibus / Coach / Bus | D112: AIA - if £1m used up in the year then based on emissions rules | E112: Put in AIA, and when AIA limit of £1m used up in that tax year, but in pool depending on emissions | F112: Business use, AIA allowance - If used If business use <100%, ensure you only take business percentage
A113: N1 | B113: Depends | C113: Van / Pickup (≤ 3.5t) | D113: AIA - if £1m used up in the year then based on emissions rules | E113: Put in AIA, and when AIA limit of £1m used up in that tax year, but in pool depending on emissions | F113: Business use, AIA allowance - If used If business use <100%, ensure you only take business percentage
A114: N2 / N3 | B114: Depends | C114: Medium/Heavy Goods Vehicle | D114: AIA - if £1m used up in the year then based on emissions rules | E114: Put in AIA, and when AIA limit of £1m used up in that tax year, but in pool depending on emissions | F114: Business use, AIA allowance - If used If business use <100%, ensure you only take business percentage
A115: L1e / L2e | B115: Depends | C115: Moped / 3-Wheel Moped | D115: AIA - if £1m used up in the year then based on emissions rules | E115: Put in AIA, and when AIA limit of £1m used up in that tax year, but in pool depending on emissions | F115: Business use, AIA allowance - If used If business use <100%, ensure you only take business percentage
A116: L3e – L5e | B116: Depends | C116: Motorcycle / Trike / Sidecar | D116: AIA - if £1m used up in the year then based on emissions rules | E116: Put in AIA, and when AIA limit of £1m used up in that tax year, but in pool depending on emissions | F116: Business use, AIA allowance - If used If business use <100%, ensure you only take business percentage
A117: L6e / L7e | B117: Depends | C117: Quadricycles / Microcars | D117: AIA - if £1m used up in the year then based on emissions rules | E117: Put in AIA, and when AIA limit of £1m used up in that tax year, but in pool depending on emissions | F117: Business use, AIA allowance - If used If business use <100%, ensure you only take business percentage
A118: O1 – O4 | B118: Depends | C118: Trailers | D118: AIA - if £1m used up in the year then based on emissions rules | E118: Put in AIA, and when AIA limit of £1m used up in that tax year, but in pool depending on emissions | F118: Business use, AIA allowance - If used If business use <100%, ensure you only take business percentage
A119: T | B119: Depends | C119: Agricultural tractor | D119: AIA - if £1m used up in the year then based on emissions rules | E119: Put in AIA, and when AIA limit of £1m used up in that tax year, but in pool depending on emissions | F119: Business use, AIA allowance - If used If business use <100%, ensure you only take business percentage

Sheet Allow&Disa Exp by Truelayer cat
A1: TrueLayer classification category | B1: Classification Subcategory | C1: Allowable/Disallowable or Review | D1: IntelliBooks Prompt | E1: What IB must do in the background
A2: Cash | B2: Cash & ATM | C2: Review | D2: "Taking out cash? Let's find out if it was for business or just your weekend vibes." | E2: If not for trade, then disallow and add back to income. - Prompt user to add receipt for VAT or just evidence
A3: Cash | B3: Check | C3: Review | D3: "Can you help me with this?" | E3: If not for trade, then disallow and add back to income. - Prompt user to add receipt for VAT or just evidence
A4: Entertainment | B4: Arts | C4: Disallowable | E4: Add back to income
A5: Entertainment | B5: Music | C5: Review | D5: "Is this music for business…or just to keep you dancing while doing the dishes?" | E5: If not for trade, then disallow and add back to income. - Prompt user to add receipt for VAT or just evidence
A6: Entertainment | B6: Dating | C6: Disallowable | E6: Add back to income
A7: Entertainment | B7: Movies & DVDs | C7: Review | D7: "Was this purchase for trade purposes?" | E7: If not for trade, then disallow and add back to income. - Prompt user to add receipt for VAT or just evidence
A8: Entertainment | B8: Newspaper & Magazines | C8: Review | D8: "Is this magazine helping your business….or just your Sunday chill?" | E8: If not for trade, then disallow and add back to income. - Prompt user to add receipt for VAT or just evidence
A9: Entertainment | B9: Social Club | C9: Disallowable | E9: Add back to income
A10: Entertainment | B10: Sport | C10: Disallowable | E10: Add back to income
A11: Entertainment | B11: Games | C11: Disallowable | E11: Add back to income
A12: Education | B12: Tuition | C12: Review | D12: "Is this tuition of training related to your business or trade?" | E12: If not for trade, then disallow and add back to income. - Prompt user to add receipt for VAT or just evidence
A13: Education | B13: Student Loan | C13: Review | D13: "Is this tuition of training related to your business or trade?" | E13: If not for trade, then disallow and add back to income. - Prompt user to add receipt for VAT or just evidence
A14: Education | B14: Books & Supplies | C14: Allowable | D14: "Are these books for trade?...or just for free time?" | E14: If not for trade, then disallow and add back to income. - Prompt user to add receipt for VAT or just evidence
A15: Shopping | B15: Pets | C15: Disallowable | E15: Add back to income
A16: Shopping | B16: Groceries | C16: Review | D16: "We see you've bought some groceries! Was this grocery haul fuel for your business….or just dinner?" | E16: If not for trade, then disallow and add back to income. - Prompt user to add receipt for VAT or just evidence
A17: Shopping | B17: General | C17: Review | D17: "Oh! Im not sure what this may be. Help me with this and I sure won't forget the next time" (Then give listing of what is shown in this list, and then ask if this is for trade.) | E17: If not for trade, then disallow and add back to income. - Prompt user to add receipt for VAT or just evidence
A18: Shopping | B18: Clothing | C18: Review | D18: "Is this something your business needs….or just a nice fit?" | E18: If not for trade, then disallow and add back to income. - Prompt user to add receipt for VAT or just evidence
A19: Shopping | B19: Home | C19: Review | D19: "Was this purchase for trade purposes?" | E19: If not for trade, then disallow and add back to income. - Prompt user to add receipt for VAT or just evidence
A20: Shopping | B20: Books | C20: Review | D20: "Was this purchase for trade purposes?" | E20: If not for trade, then disallow and add back to income. - Prompt user to add receipt for VAT or just evidence
A21: Shopping | B21: Electronics & Software | C21: Allowable if under £500 | E21: Deduct from expenses if under £500
A22: Shopping | B22: Electronics & Software | C22: Review (If over >500) | D22: "This looks like an asset purchase, please help me with what this is for correct tax treatment" | E22: If not for trade, then disallow and add back to income. - Prompt user to add receipt for VAT or just evidence - If for devices then Capital allowances. If software used for trade > allowable expense if >£500 then this should trigger capital allowance questions
A23: Shopping | B23: Hobbies | C23: Disallowable | E23: Add back to income
A24: Shopping | B24: Sporting Goods | C24: Disallowable | E24: Add back to income
A25: Personal Care | B25: Hair | C25: Disallowable | E25: Add back to income
A26: Personal Care | B26: Laundry | C26: Review | D26: "Was this purchase for trade purposes?" | E26: If not for trade, then disallow and add back to income. - Prompt user to add receipt for VAT or just evidence
A27: Personal Care | B27: Beauty | C27: Disallowable | E27: Add back to income
A28: Personal Care | B28: Spa & Massage | C28: Disallowable | E28: Add back to income
A29: Health & Fitness | B29: Dentist | C29: Review | D29: "Was this purchase for trade purposes?" | E29: Add back to income
A30: Health & Fitness | B30: Doctor | C30: Allowable | E30: Deduct from expenses
A31: Health & Fitness | B31: Eye care | C31: Review | D31: "Was this purchase for trade purposes?" | E31: Add back to income
A32: Health & Fitness | B32: Pharmacy | C32: Allowable | E32: Deduct from expenses
A33: Health & Fitness | B33: Gym | C33: Disallowable | E33: Add back to income
A34: Health & Fitness | B34: Pets | C34: Disallowable | E34: Add back to income
A35: Health & Fitness | B35: Sports | C35: Disallowable | E35: Add back to income
A36: Food & Dining | B36: Catering | C36: Review | D36: "Was this purchase for trade purposes?" | E36: If not for trade, then disallow and add back to income. - Prompt user to add receipt for VAT or just evidence
A37: Food & Dining | B37: Coffee shops | C37: Review | D37: "Was this purchase for trade purposes?" | E37: Add back to income
A38: Food & Dining | B38: Delivery | C38: Review | D38: "Was this purchase for trade purposes?" | E38: If not for trade, then disallow and add back to income. - Prompt user to add receipt for VAT or just evidence
A39: Food & Dining | B39: Fast Food | C39: Review | D39: "Was this purchase for trade purposes?" | E39: Add back to income
A40: Food & Dining | B40: Restaurants | C40: Review | D40: "Was this purchase for trade purposes?" | E40: If not for trade, then disallow and add back to income. - Prompt user to add receipt for VAT or just evidence
A41: Food & Dining | B41: Bars | C41: Review | D41: "Was this purchase for trade purposes?" | E41: Add back to income
A42: Gifts & Donations | B42: Gift | C42: Review | D42: "Was this donation made personally using Gift Aid or paid directly from your business account?" | E42: If directly paid from busines account then not for trade, disallow and add back to income.
A43: Gifts & Donations | B43: Charity | C43: Review | D43: "Did you tick the gift aid box when making this donation?" | E43: If yes allowable, if not ticked then do not include this donation in calculations - Do not add back to income either as its not disallowable.
A44: Investments | B44: Equities | C44: Review | D44: "Was this purchase for trade purposes?" | E44: If not for trade, then disallow and add back to income. - Prompt user to add receipt for VAT or just evidence
A45: Investments | B45: Bonds | C45: Review | D45: "Was this purchase for trade purposes?" | E45: If not for trade, then disallow and add back to income. - Prompt user to add receipt for VAT or just evidence
A46: Investments | B46: Bank products | C46: Review | D46: "Was this purchase for trade purposes?" | E46: If not for trade, then disallow and add back to income. - Prompt user to add receipt for VAT or just evidence
A47: Investments | B47: Retirement | C47: Review | D47: "Was this purchase for trade purposes?" | E47: If not for trade, then disallow and add back to income. - Prompt user to add receipt for VAT or just evidence
... A50: Bills & Utilities | B50: Television | C50: Review | D50: "Was this purchase for trade purposes?" | E50: If not for trade, then disallow and add back to income. - Prompt user to add receipt for VAT or just evidence
A51: Bills & Utilities | B51: Home Phone | C51: Allowable | E51: Deduct from expenses
A52: Bills & Utilities | B52: Internet | C52: Allowable | E52: Deduct from expenses
A53: Bills & Utilities | B53: Mobile Phone | C53: Allowable | E53: Deduct from expenses
A54: Bills & Utilities | B54: Utilities | C54: Allowable | E54: Deduct from expenses
A55: Auto & Transport | B55: Auto Insurance | C55: Allowable | E55: Deduct from expenses
A56: Auto & Transport | B56: Auto Payment | C56: Allowable | E56: Deduct from expenses
A57: Auto & Transport | B57: Parking | C57: Review | D57: "Was this paying to park your car…or paying for parking it badly?" | E57: If parking fine DISALLOW. If not then deduct
A58: Auto & Transport | B58: Public transport | C58: Allowable | E58: Deduct from expenses
A59: Auto & Transport | B59: Service & Auto Parts | C59: Review if over >1,000 | D59: "Could this be a vehicle purchase?" - If user says no - "Was this purchase for trade purposes?" | E59: If Yes to vehicle purchase, then proceed Capital allowancesquestions (in capital allowance page) if yes for trade, deduct from expenses
A60: Auto & Transport | B60: Taxi | C60: Allowable | E60: Deduct from expenses
A61: Auto & Transport | B61: Gas & Fuel | C61: Allowable | E61: Deduct from expenses
A62: Travel | B62: Air Travel | C62: Allowable | E62: Deduct from expenses
A63: Travel | B63: Hotel | C63: Allowable | E63: Deduct from expenses
A64: Travel | B64: Rental Car & Taxi | C64: Allowable | E64: Deduct from expenses
A65: Travel | B65: Vacation | C65: Review | D65: "Was this purchase for trade purposes?" | E65: If not for trade, then disallow and add back to income. - Prompt user to add receipt for VAT or just evidence
A66: Fees & Charges | B66: Service Fee | C66: Allowable | E66: Deduct from expenses
A67: Fees & Charges | B67: Late Fee | C67: Disallowable | E67: Add back to income
A68: Fees & Charges | B68: Finance Charge | C68: Allowable | E68: Deduct from expenses
A69: Fees & Charges | B69: ATM Fee | C69: Disallowable | E69: Add back to income
A70: Fees & Charges | B70: Bank Fee | C70: Allowable | E70: Deduct from expenses
A71: Fees & Charges | B71: Commissions | C71: Allowable | E71: Deduct from expenses
A72: Fines & Penalties | B72: Fines & Penalties | C72: Disallowable | E72: Add back to income
A73: Business Services | B73: Advertising | C73: Allowable | E73: Deduct from expenses
A74: Business Services | B74: Financial Services | C74: Allowable | E74: Deduct from expenses
A75: Business Services | B75: Office Supplies | C75: Allowable | E75: Deduct from expenses
A76: Business Services | B76: Printing | C76: Allowable | E76: Deduct from expenses
A77: Business Services | B77: Shipping | C77: Allowable | E77: Deduct from expenses
... A89: Home | B89: Rent | C89: Allowable | E89: Deduct from expenses
A90: Home | B90: Mortgage Costs | C90: Review (If same amount goues out to bank or building society monthly) | D90: "You may be eligible for mortgage interest relief, since your income is an FHL, Can I have a breakdown of the mortgage interest on these payments? These are 100% deductible and will save you tax!" Then also give user as option to ask where they can get this information - "If you do not have this on your Lender's online portal, please ask them for a copy of this document. We would also need to retain this for HMRC" | E90: If uploaded by user OCR detects Interest element and records the amount relating to te tax year.
A91: Home | B91: Secured loans | C91: Review | D91: "Was this cost for trade purposes?" | E91: If not for trade, then disallow and add back to income. - Prompt user to add receipt for VAT or just evidence
A92: Home | B92: Mortgage Interest | C92: Split out when user states interest amount on payment | D92: "You may be eligible for mortgage interest relief, since your income is an FHL, Can I have a breakdown of the mortgage interest on these payments? These are 100% deductible and will save you tax!" Then also give user as option to ask where they can get this information - "If you do not have this on your Lender's online portal, please ask them for a copy of this document. We would also need to retain this for HMRC" | E92: If uploaded by user OCR detects Interest element and records the amount relating to the tax year.
A93: Pensions and Insurances | B93: Pension payments (UK Registered) | C93: Allowable | E93: Deduct from expenses
A94: Pensions and Insurances | B94: Pension payments (Not - UK Registered) | C94: N/A | D94: "Is this a private pension provider?, If so there will be no relief on this transaction, try contributing to a UK registered pension provider to reduce your tax liability." | E94: Just record in Financial statements LEAVE OUT OF TAX CALCULATIONS
A95: Pensions and Insurances | B95: Life insurance | C95: Allowable | E95: Deduct from expenses
A96: Pensions and Insurances | B96: Buildings and contents insurance | C96: Allowable | E96: Deduct from expenses
A97: Pensions and Insurances | B97: Health insurance | C97: Allowable | E97: Deduct from expenses
A98: *Based on merchant or ML | B98: Salaries | C98: Allowable | E98: Deduct from expenses (Check for expense being over £1k) - If over £1K, likely to be Salary PAID ,which is allowable, - ALSO CHECK IF SALARY IS BEING SENT TO PARTNER (IF RECIPIENT NAME MATCHES partner name in any way, take this as drawings and change the share allocation {Check drawings calculations tab})
A99: *Based on merchant or ML | B99: HR Fees | C99: Allowable | E99: Deduct from expenses
A100: *Based on merchant or ML | B100: Accounting Fees | C100: Allowable | E100: Deduct from expenses
A101: *Based on name match to partner | B101: Drawings | C101: N/A - Take original capital figure from bank transaction if brand new (i.e fuzzy matching on PAYER'S name to OWNERS NAME IF BIG BANK AMOUNT check surname, forename) - But if coming from another system use TB amount showing for "DRAWINGS" - Adjustments made check any amounts going to any named partner and adjust accordingly. | E101: Just adjust in Balance Sheet
A104: If N/A | B104: Nothing to do with tax, cannot add or subtract. Leave it out of calculations completely for tax
A105: Allowable | B105: Deduct from total taxable income
A106: Dissallowable | B106: Add back to income

Sheet Allow&Disa Exp by Merchant
A1: MERCHANT LISTING | H1: In case our subcategories do not work, the merchant listing will help us identify where they should go for tax and for accounting purposes - This is the fallback in case the first way of categorising fails.
A2: Group | B2: Name | C2: Category | D2: Allowable/Dissallowable | E2: IntelliBooks Prompt | F2: What IB must do in the background
A3: Car Brands (Automotive should b | B3: Abarth | C3: Service & Auto Parts | D3: =_xlfn.XLOOKUP(C3,'Allow&Disa Exp by Truelayer cat'!$B:$B,'Allow&Disa Exp by Truelayer cat'!$C:$C) -> Review if over >1,000 | E3: =_xlfn.XLOOKUP(C3,'Allow&Disa Exp by Truelayer cat'!$B:$B,'Allow&Disa Exp by Truelayer cat'!$D:$D) -> "Could this be a vehicle purchase?" - If user says no - "Was this purchase for trade purposes?" | F3: =_xlfn.XLOOKUP(C3,'Allow&Disa Exp by Truelayer cat'!$B:$B,'Allow&Disa Exp by Truelayer cat'!$E:$E) -> If Yes to vehicle purchase, then proceed Capital allowancesquestions (in capital allowance page) if yes for trade, deduct from expenses | H3: To make this work we have to use FUZZY MATCHING - This will help with ensuring the transaction is matched regardless of the string form.
A4: Car Brands (Automotive should b | B4: Alfa Romeo | C4: Service & Auto Parts | D4: =_xlfn.XLOOKUP(C4,'Allow&Disa Exp by Truelayer cat'!$B:$B,'Allow&Disa Exp by Truelayer cat'!$C:$C) -> Review if over >1,000 | E4: =_xlfn.XLOOKUP(C4,'Allow&Disa Exp by Truelayer cat'!$B:$B,'Allow&Disa Exp by Truelayer cat'!$D:$D) -> "Could this be a vehicle purchase?" - If user says no - "Was this purchase for trade purposes?" | F4: =_xlfn.XLOOKUP(C4,'Allow&Disa Exp by Truelayer cat'!$B:$B,'Allow&Disa Exp by Truelayer cat'!$E:$E) -> If Yes to vehicle purchase, then proceed Capital allowancesquestions (in capital allowance page) if yes for trade, deduct from expenses | H4: ✅ What is Fuzzy Matching?
A5: Car Brands (Automotive should b | B5: Alpine | C5: Service & Auto Parts | D5: =_xlfn.XLOOKUP(C5,'Allow&Disa Exp by Truelayer cat'!$B:$B,'Allow&Disa Exp by Truelayer cat'!$C:$C) -> Review if over >1,000 | E5: =_xlfn.XLOOKUP(C5,'Allow&Disa Exp by Truelayer cat'!$B:$B,'Allow&Disa Exp by Truelayer cat'!$D:$D) -> "Could this be a vehicle purchase?" - If user says no - "Was this purchase for trade purposes?" | F5: =_xlfn.XLOOKUP(C5,'Allow&Disa Exp by Truelayer cat'!$B:$B,'Allow&Disa Exp by Truelayer cat'!$E:$E) -> If Yes to vehicle purchase, then proceed Capital allowancesquestions (in capital allowance page) if yes for trade, deduct from expenses
A6: Car Brands (Automotive should b | B6: Aston Martin | C6: Service & Auto Parts | D6: =_xlfn.XLOOKUP(C6,'Allow&Disa Exp by Truelayer cat'!$B:$B,'Allow&Disa Exp by Truelayer cat'!$C:$C) -> Review if over >1,000 | E6: =_xlfn.XLOOKUP(C6,'Allow&Disa Exp by Truelayer cat'!$B:$B,'Allow&Disa Exp by Truelayer cat'!$D:$D) -> "Could this be a vehicle purchase?" - If user says no - "Was this purchase for trade purposes?" | F6: =_xlfn.XLOOKUP(C6,'Allow&Disa Exp by Truelayer cat'!$B:$B,'Allow&Disa Exp by Truelayer cat'!$E:$E) -> If Yes to vehicle purchase, then proceed Capital allowancesquestions (in capital allowance page) if yes for trade, deduct from expenses | H6: Fuzzy matching is the process of identifying approximate rather than exact matches between strings. This is crucial for:
A7: Car Brands (Automotive should b | B7: Audi | C7: Service & Auto Parts | D7: =_xlfn.XLOOKUP(C7,'Allow&Disa Exp by Truelayer cat'!$B:$B,'Allow&Disa Exp by Truelayer cat'!$C:$C) -> Review if over >1,000 | E7: =_xlfn.XLOOKUP(C7,'Allow&Disa Exp by Truelayer cat'!$B:$B,'Allow&Disa Exp by Truelayer cat'!$D:$D) -> "Could this be a vehicle purchase?" - If user says no - "Was this purchase for trade purposes?" | F7: =_xlfn.XLOOKUP(C7,'Allow&Disa Exp by Truelayer cat'!$B:$B,'Allow&Disa Exp by Truelayer cat'!$E:$E) -> If Yes to vehicle purchase, then proceed Capital allowancesquestions (in capital allowance page) if yes for trade, deduct from expenses
A8: Car Brands (Automotive should b | B8: Bentley | C8: Service & Auto Parts | D8: =_xlfn.XLOOKUP(C8,'Allow&Disa Exp by Truelayer cat'!$B:$B,'Allow&Disa Exp by Truelayer cat'!$C:$C) -> Review if over >1,000 | E8: =_xlfn.XLOOKUP(C8,'Allow&Disa Exp by Truelayer cat'!$B:$B,'Allow&Disa Exp by Truelayer cat'!$D:$D) -> "Could this be a vehicle purchase?" - If user says no - "Was this purchase for trade purposes?" | F8: =_xlfn.XLOOKUP(C8,'Allow&Disa Exp by Truelayer cat'!$B:$B,'Allow&Disa Exp by Truelayer cat'!$E:$E) -> If Yes to vehicle purchase, then proceed Capital allowancesquestions (in capital allowance page) if yes for trade, deduct from expenses | H8: Matching noisy, inconsistent, or abbreviated data (e.g., RYANAIR DAC 12345)
A9: Car Brands (Automotive should b | B9: BMW | C9: Service & Auto Parts | D9: =_xlfn.XLOOKUP(C9,'Allow&Disa Exp by Truelayer cat'!$B:$B,'Allow&Disa Exp by Truelayer cat'!$C:$C) -> Review if over >1,000 | E9: =_xlfn.XLOOKUP(C9,'Allow&Disa Exp by Truelayer cat'!$B:$B,'Allow&Disa Exp by Truelayer cat'!$D:$D) -> "Could this be a vehicle purchase?" - If user says no - "Was this purchase for trade purposes?" | F9: =_xlfn.XLOOKUP(C9,'Allow&Disa Exp by Truelayer cat'!$B:$B,'Allow&Disa Exp by Truelayer cat'!$E:$E) -> If Yes to vehicle purchase, then proceed Capital allowancesquestions (in capital allowance page) if yes for trade, deduct from expenses
A10: Car Brands (Automotive should b | B10: BYD | C10: Service & Auto Parts | D10: =_xlfn.XLOOKUP(C10,'Allow&Disa Exp by Truelayer cat'!$B:$B,'Allow&Disa Exp by Truelayer cat'!$C:$C) -> Review if over >1,000 | E10: =_xlfn.XLOOKUP(C10,'Allow&Disa Exp by Truelayer cat'!$B:$B,'Allow&Disa Exp by Truelayer cat'!$D:$D) -> "Could this be a vehicle purchase?" - If user says no - "Was this purchase for trade purposes?" | F10: =_xlfn.XLOOKUP(C10,'Allow&Disa Exp by Truelayer cat'!$B:$B,'Allow&Disa Exp by Truelayer cat'!$E:$E) -> If Yes to vehicle purchase, then proceed Capital allowancesquestions (in capital allowance page) if yes for trade, deduct from expenses | H10: Handling typos, different word orders, suffixes, etc.
A11: Car Brands (Automotive should b | B11: Caterham | C11: Service & Auto Parts | D11: =_xlfn.XLOOKUP(C11,'Allow&Disa Exp by Truelayer cat'!$B:$B,'Allow&Disa Exp by Truelayer cat'!$C:$C) -> Review if over >1,000 | E11: =_xlfn.XLOOKUP(C11,'Allow&Disa Exp by Truelayer cat'!$B:$B,'Allow&Disa Exp by Truelayer cat'!$D:$D) -> "Could this be a vehicle purchase?" - If user says no - "Was this purchase for trade purposes?" | F11: =_xlfn.XLOOKUP(C11,'Allow&Disa Exp by Truelayer cat'!$B:$B,'Allow&Disa Exp by Truelayer cat'!$E:$E) -> If Yes to vehicle purchase, then proceed Capital allowancesquestions (in capital allowance page) if yes for trade, deduct from expenses
A12: Car Brands (Automotive should b | B12: Citroën | C12: Service & Auto Parts | D12: =_xlfn.XLOOKUP(C12,'Allow&Disa Exp by Truelayer cat'!$B:$B,'Allow&Disa Exp by Truelayer cat'!$C:$C) -> Review if over >1,000 | E12: =_xlfn.XLOOKUP(C12,'Allow&Disa Exp by Truelayer cat'!$B:$B,'Allow&Disa Exp by Truelayer cat'!$D:$D) -> "Could this be a vehicle purchase?" - If user says no - "Was this purchase for trade purposes?" | F12: =_xlfn.XLOOKUP(C12,'Allow&Disa Exp by Truelayer cat'!$B:$B,'Allow&Disa Exp by Truelayer cat'!$E:$E) -> If Yes to vehicle purchase, then proceed Capital allowancesquestions (in capital allowance page) if yes for trade, deduct from expenses
A13: Car Brands (Automotive should b | B13: Cupra | C13: Service & Auto Parts | D13: =_xlfn.XLOOKUP(C13,'Allow&Disa Exp by Truelayer cat'!$B:$B,'Allow&Disa Exp by Truelayer cat'!$C:$C) -> Review if over >1,000 | E13: =_xlfn.XLOOKUP(C13,'Allow&Disa Exp by Truelayer cat'!$B:$B,'Allow&Disa Exp by Truelayer cat'!$D:$D) -> "Could this be a vehicle purchase?" - If user says no - "Was this purchase for trade purposes?" | F13: =_xlfn.XLOOKUP(C13,'Allow&Disa Exp by Truelayer cat'!$B:$B,'Allow&Disa Exp by Truelayer cat'!$E:$E) -> If Yes to vehicle purchase, then proceed Capital allowancesquestions (in capital allowance page) if yes for trade, deduct from expenses
A14: Car Brands (Automotive should b | B14: Dacia | C14: Service & Auto Parts | D14: =_xlfn.XLOOKUP(C14,'Allow&Disa Exp by Truelayer cat'!$B:$B,'Allow&Disa Exp by Truelayer cat'!$C:$C) -> Review if over >1,000 | E14: =_xlfn.XLOOKUP(C14,'Allow&Disa Exp by Truelayer cat'!$B:$B,'Allow&Disa Exp by Truelayer cat'!$D:$D) -> "Could this be a vehicle purchase?" - If user says no - "Was this purchase for trade purposes?" | F14: =_xlfn.XLOOKUP(C14,'Allow&Disa Exp by Truelayer cat'!$B:$B,'Allow&Disa Exp by Truelayer cat'!$E:$E) -> If Yes to vehicle purchase, then proceed Capital allowancesquestions (in capital allowance page) if yes for trade, deduct from expenses
A15: Car Brands (Automotive should b | B15: DS Automobiles | C15: Service & Auto Parts | D15: =_xlfn.XLOOKUP(C15,'Allow&Disa Exp by Truelayer cat'!$B:$B,'Allow&Disa Exp by Truelayer cat'!$C:$C) -> Review if over >1,000 | E15: =_xlfn.XLOOKUP(C15,'Allow&Disa Exp by Truelayer cat'!$B:$B,'Allow&Disa Exp by Truelayer cat'!$D:$D) -> "Could this be a vehicle purchase?" - If user says no - "Was this purchase for trade purposes?" | F15: =_xlfn.XLOOKUP(C15,'Allow&Disa Exp by Truelayer cat'!$B:$B,'Allow&Disa Exp by Truelayer cat'!$E:$E) -> If Yes to vehicle purchase, then proceed Capital allowancesquestions (in capital allowance page) if yes for trade, deduct from expenses
A16: Car Brands (Automotive should b | B16: Ferrari | C16: Service & Auto Parts | D16: =_xlfn.XLOOKUP(C16,'Allow&Disa Exp by Truelayer cat'!$B:$B,'Allow&Disa Exp by Truelayer cat'!$C:$C) -> Review if over >1,000 | E16: =_xlfn.XLOOKUP(C16,'Allow&Disa Exp by Truelayer cat'!$B:$B,'Allow&Disa Exp by Truelayer cat'!$D:$D) -> "Could this be a vehicle purchase?" - If user says no - "Was this purchase for trade purposes?" | F16: =_xlfn.XLOOKUP(C16,'Allow&Disa Exp by Truelayer cat'!$B:$B,'Allow&Disa Exp by Truelayer cat'!$E:$E) -> If Yes to vehicle purchase, then proceed Capital allowancesquestions (in capital allowance page) if yes for trade, deduct from expenses
A17: Car Brands (Automotive should b | B17: Fiat | C17: Service & Auto Parts | D17: =_xlfn.XLOOKUP(C17,'Allow&Disa Exp by Truelayer cat'!$B:$B,'Allow&Disa Exp by Truelayer cat'!$C:$C) -> Review if over >1,000 | E17: =_xlfn.XLOOKUP(C17,'Allow&Disa Exp by Truelayer cat'!$B:$B,'Allow&Disa Exp by Truelayer cat'!$D:$D) -> "Could this be a vehicle purchase?" - If user says no - "Was this purchase for trade purposes?" | F17: =_xlfn.XLOOKUP(C17,'Allow&Disa Exp by Truelayer cat'!$B:$B,'Allow&Disa Exp by Truelayer cat'!$E:$E) -> If Yes to vehicle purchase, then proceed Capital allowancesquestions (in capital allowance page) if yes for trade, deduct from expenses
A18: Car Brands (Automotive should b | B18: Ford | C18: Service & Auto Parts | D18: =_xlfn.XLOOKUP(C18,'Allow&Disa Exp by Truelayer cat'!$B:$B,'Allow&Disa Exp by Truelayer cat'!$C:$C) -> Review if over >1,000 | E18: =_xlfn.XLOOKUP(C18,'Allow&Disa Exp by Truelayer cat'!$B:$B,'Allow&Disa Exp by Truelayer cat'!$D:$D) -> "Could this be a vehicle purchase?" - If user says no - "Was this purchase for trade purposes?" | F18: =_xlfn.XLOOKUP(C18,'Allow&Disa Exp by Truelayer cat'!$B:$B,'Allow&Disa Exp by Truelayer cat'!$E:$E) -> If Yes to vehicle purchase, then proceed Capital allowancesquestions (in capital allowance page) if yes for trade, deduct from expenses
A19: Car Brands (Automotive should b | B19: GMC | C19: Service & Auto Parts | D19: =_xlfn.XLOOKUP(C19,'Allow&Disa Exp by Truelayer cat'!$B:$B,'Allow&Disa Exp by Truelayer cat'!$C:$C) -> Review if over >1,000 | E19: =_xlfn.XLOOKUP(C19,'Allow&Disa Exp by Truelayer cat'!$B:$B,'Allow&Disa Exp by Truelayer cat'!$D:$D) -> "Could this be a vehicle purchase?" - If user says no - "Was this purchase for trade purposes?" | F19: =_xlfn.XLOOKUP(C19,'Allow&Disa Exp by Truelayer cat'!$B:$B,'Allow&Disa Exp by Truelayer cat'!$E:$E) -> If Yes to vehicle purchase, then proceed Capital allowancesquestions (in capital allowance page) if yes for trade, deduct from expenses
A20: Car Brands (Automotive should b | B20: Honda | C20: Service & Auto Parts | D20: =_xlfn.XLOOKUP(C20,'Allow&Disa Exp by Truelayer cat'!$B:$B,'Allow&Disa Exp by Truelayer cat'!$C:$C) -> Review if over >1,000 | E20: =_xlfn.XLOOKUP(C20,'Allow&Disa Exp by Truelayer cat'!$B:$B,'Allow&Disa Exp by Truelayer cat'!$D:$D) -> "Could this be a vehicle purchase?" - If user says no - "Was this purchase for trade purposes?" | F20: =_xlfn.XLOOKUP(C20,'Allow&Disa Exp by Truelayer cat'!$B:$B,'Allow&Disa Exp by Truelayer cat'!$E:$E) -> If Yes to vehicle purchase, then proceed Capital allowancesquestions (in capital allowance page) if yes for trade, deduct from expenses
A21: Car Brands (Automotive should b | B21: Hyundai | C21: Service & Auto Parts | D21: =_xlfn.XLOOKUP(C21,'Allow&Disa Exp by Truelayer cat'!$B:$B,'Allow&Disa Exp by Truelayer cat'!$C:$C) -> Review if over >1,000 | E21: =_xlfn.XLOOKUP(C21,'Allow&Disa Exp by Truelayer cat'!$B:$B,'Allow&Disa Exp by Truelayer cat'!$D:$D) -> "Could this be a vehicle purchase?" - If user says no - "Was this purchase for trade purposes?" | F21: =_xlfn.XLOOKUP(C21,'Allow&Disa Exp by Truelayer cat'!$B:$B,'Allow&Disa Exp by Truelayer cat'!$E:$E) -> If Yes to vehicle purchase, then proceed Capital allowancesquestions (in capital allowance page) if yes for trade, deduct from expenses
A22: Car Brands (Automotive should b | B22: Infiniti | C22: Service & Auto Parts | D22: =_xlfn.XLOOKUP(C22,'Allow&Disa Exp by Truelayer cat'!$B:$B,'Allow&Disa Exp by Truelayer cat'!$C:$C) -> Review if over >1,000 | E22: =_xlfn.XLOOKUP(C22,'Allow&Disa Exp by Truelayer cat'!$B:$B,'Allow&Disa Exp by Truelayer cat'!$D:$D) -> "Could this be a vehicle purchase?" - If user says no - "Was this purchase for trade purposes?" | F22: =_xlfn.XLOOKUP(C22,'Allow&Disa Exp by Truelayer cat'!$B:$B,'Allow&Disa Exp by Truelayer cat'!$E:$E) -> If Yes to vehicle purchase, then proceed Capital allowancesquestions (in capital allowance page) if yes for trade, deduct from expenses
... A1004: Legal Platforms | B1004: Garfield AI | C1004: Legal Fees | D1004: =_xlfn.XLOOKUP(C1004,'Allow&Disa Exp by Truelayer cat'!$B:$B,'Allow&Disa Exp by Truelayer cat'!$C:$C) -> Allowable | E1004: =_xlfn.XLOOKUP(C1004,'Allow&Disa Exp by Truelayer cat'!$B:$B,'Allow&Disa Exp by Truelayer cat'!$D:$D) -> 0 | F1004: =_xlfn.XLOOKUP(C1004,'Allow&Disa Exp by Truelayer cat'!$B:$B,'Allow&Disa Exp by Truelayer cat'!$E:$E) -> Deduct from expenses

Sheet Transaction Cat for Tax&FS
A1: TrueLayer classification category | B1: Classification Subcategory | C1: Financial Statements | D1: FS Sub Category | E1: API Name: | F1: Allowable/Disallowable or Review | G1: IntelliBooks Prompt | H1: What IB must do in the background
A2: Cash | B2: Cash & ATM | C2: Balance Sheet | D2: Cash at Bank | E2: 0 | F2: Review | G2: "Taking out cash? Let's find out if it was for business or just your weekend vibes." | H2: If not for trade, then disallow and add back to income. - Prompt user to add receipt for VAT or just evidence
A3: Cash | B3: Check | C3: Balance Sheet | D3: Cash at Bank | E3: selfEmployment.expenses.entertaining | F3: Review | G3: "Can you help me with this?" | H3: If not for trade, then disallow and add back to income. - Prompt user to add receipt for VAT or just evidence
A4: Entertainment | B4: Arts | C4: Profit and Loss | D4: Expenses | E4: selfEmployment.expenses.entertaining | F4: Disallowable | H4: Add back to income
A5: Entertainment | B5: Music | C5: Profit and Loss | D5: Expenses | E5: selfEmployment.expenses.entertaining | F5: Review | G5: "Is this music for business…or just to keep you dancing while doing the dishes?" | H5: If not for trade, then disallow and add back to income. - Prompt user to add receipt for VAT or just evidence
A6: Entertainment | B6: Dating | C6: Profit and Loss | D6: Expenses | E6: selfEmployment.expenses.entertaining | F6: Disallowable | H6: Add back to income
A7: Entertainment | B7: Movies & DVDs | C7: Profit and Loss | D7: Expenses | E7: selfEmployment.expenses.adminCosts | F7: Review | G7: "Was this purchase for trade purposes?" | H7: If not for trade, then disallow and add back to income. - Prompt user to add receipt for VAT or just evidence
A8: Entertainment | B8: Newspaper & Magazines | C8: Profit and Loss | D8: Expenses | E8: selfEmployment.expenses.staffWelfare | F8: Review | G8: "Is this magazine helping your business….or just your Sunday chill?" | H8: If not for trade, then disallow and add back to income. - Prompt user to add receipt for VAT or just evidence
A9: Entertainment | B9: Social Club | C9: Profit and Loss | D9: Expenses | E9: selfEmployment.expenses.entertaining | F9: Disallowable | H9: Add back to income
A10: Entertainment | B10: Sport | C10: Profit and Loss | D10: Expenses | E10: selfEmployment.expenses.entertaining | F10: Disallowable | H10: Add back to income
A11: Entertainment | B11: Games | C11: Profit and Loss | D11: Expenses | E11: selfEmployment.expenses.trainingCourses | F11: Disallowable | H11: Add back to income
A12: Education | B12: Tuition | C12: Profit and Loss | D12: Expenses | E12: 0 | F12: Review | G12: "Is this tuition of training related to your business or trade?" | H12: If not for trade, then disallow and add back to income. - Prompt user to add receipt for VAT or just evidence
A13: Education | B13: Student Loan | C13: Profit and Loss | D13: Expenses | E13: selfEmployment.expenses.adminCosts | F13: Review | G13: "Is this tuition of training related to your business or trade?" | H13: If not for trade, then disallow and add back to income. - Prompt user to add receipt for VAT or just evidence
A14: Education | B14: Books & Supplies | C14: Profit and Loss | D14: Expenses | E14: 0 | F14: Allowable | G14: "Are these books for trade?...or just for free time?" | H14: If not for trade, then disallow and add back to income. - Prompt user to add receipt for VAT or just evidence
A15: Shopping | B15: Pets | C15: Profit and Loss | D15: Expenses | E15: 0 | F15: Disallowable | H15: Add back to income
A16: Shopping | B16: Groceries | C16: Profit and Loss | D16: Expenses | E16: selfEmployment.expenses.other | F16: Review | G16: "We see you've bought some groceries! Was this grocery haul fuel for your business….or just dinner?" | H16: If not for trade, then disallow and add back to income. - Prompt user to add receipt for VAT or just evidence
A17: Shopping | B17: General | C17: Profit and Loss | D17: Expenses | E17: 0 | F17: Review | G17: "Oh! Im not sure what this may be. Help me with this and I sure won't forget the next time" (Then give listing of what is shown in this list, and then ask if this is for trade.) | H17: If not for trade, then disallow and add back to income. - Prompt user to add receipt for VAT or just evidence
A18: Shopping | B18: Clothing | C18: Profit and Loss | D18: Expenses | E18: 0 | F18: Review | G18: "Is this something your business needs….or just a nice fit?" | H18: If not for trade, then disallow and add back to income. - Prompt user to add receipt for VAT or just evidence
A19: Shopping | B19: Home | C19: Profit and Loss | D19: Expenses | E19: selfEmployment.expenses.adminCosts | F19: Review | G19: "Was this purchase for trade purposes?" | H19: If not for trade, then disallow and add back to income. - Prompt user to add receipt for VAT or just evidence
A20: Shopping | B20: Books | C20: Profit and Loss | D20: Expenses | E20: selfEmployment.expenses.adminCosts | F20: Review | G20: "Was this purchase for trade purposes?" | H20: If not for trade, then disallow and add back to income. - Prompt user to add receipt for VAT or just evidence
A21: Shopping | B21: Electronics & Software | C21: Profit and Loss | D21: Expenses | E21: selfEmployment.expenses.adminCosts | F21: Allowable if under £500 | H21: Deduct from expenses if under £500
A22: Shopping | B22: Electronics & Software | C22: Balance Sheet | D22: Asset | E22: 0 | F22: Review (If over >500) | G22: "This looks like an asset purchase, please help me with what this is for correct tax treatment" | H22: If not for trade, then disallow and add back to income. - Prompt user to add receipt for VAT or just evidence - If for devices then Capital allowances. If software used for trade > allowable expense if >£500 then this should trigger capital allowance questions
A23: Shopping | B23: Hobbies | C23: Profit and Loss | D23: Expenses | E23: 0 | F23: Disallowable | H23: Add back to income
A24: Shopping | B24: Sporting Goods | C24: Profit and Loss | D24: Expenses | E24: 0 | F24: Disallowable | H24: Add back to income
A25: Personal Care | B25: Hair | C25: Profit and Loss | D25: Expenses | E25: 0 | F25: Disallowable | H25: Add back to income
A26: Personal Care | B26: Laundry | C26: Profit and Loss | D26: Expenses | E26: 0 | F26: Review | G26: "Was this purchase for trade purposes?" | H26: If not for trade, then disallow and add back to income. - Prompt user to add receipt for VAT or just evidence
A27: Personal Care | B27: Beauty | C27: Profit and Loss | D27: Expenses | E27: 0 | F27: Disallowable | H27: Add back to income
A28: Personal Care | B28: Spa & Massage | C28: Profit and Loss | D28: Expenses | E28: 0 | F28: Disallowable | H28: Add back to income
A29: Health & Fitness | B29: Dentist | C29: Profit and Loss | D29: Expenses | E29: 0 | F29: Review | G29: "Was this purchase for trade purposes?" | H29: Add back to income
A30: Health & Fitness | B30: Doctor | C30: Profit and Loss | D30: Expenses | E30: 0 | F30: Allowable | H30: Deduct from expenses
A31: Health & Fitness | B31: Eye care | C31: Profit and Loss | D31: Expenses | E31: 0 | F31: Review | G31: "Was this purchase for trade purposes?" | H31: Add back to income
A32: Health & Fitness | B32: Pharmacy | C32: Profit and Loss | D32: Expenses | E32: 0 | F32: Allowable | H32: Deduct from expenses
A33: Health & Fitness | B33: Gym | C33: Profit and Loss | D33: Expenses | E33: 0 | F33: Disallowable | H33: Add back to income
A34: Health & Fitness | B34: Pets | C34: Profit and Loss | D34: Expenses | E34: 0 | F34: Disallowable | H34: Add back to income
A35: Health & Fitness | B35: Sports | C35: Profit and Loss | D35: Expenses | E35: selfEmployment.expenses.other | F35: Disallowable | H35: Add back to income
A36: Food & Dining | B36: Catering | C36: Profit and Loss | D36: Expenses | E36: 0 | F36: Review | G36: "Was this purchase for trade purposes?" | H36: If not for trade, then disallow and add back to income. - Prompt user to add receipt for VAT or just evidence
A37: Food & Dining | B37: Coffee shops | C37: Profit and Loss | D37: Expenses | E37: selfEmployment.expenses.carriage | F37: Review | G37: "Was this purchase for trade purposes?" | H37: Add back to income
A38: Food & Dining | B38: Delivery | C38: Profit and Loss | D38: Expenses | E38: 0 | F38: Review | G38: "Was this purchase for trade purposes?" | H38: If not for trade, then disallow and add back to income. - Prompt user to add receipt for VAT or just evidence
A39: Food & Dining | B39: Fast Food | C39: Profit and Loss | D39: Expenses | E39: selfEmployment.expenses.entertaining | F39: Review | G39: "Was this purchase for trade purposes?" | H39: Add back to income
A40: Food & Dining | B40: Restaurants | C40: Profit and Loss | D40: Expenses | E40: selfEmployment.expenses.entertaining | F40: Review | G40: "Was this purchase for trade purposes?" | H40: If not for trade, then disallow and add back to income. - Prompt user to add receipt for VAT or just evidence
A41: Food & Dining | B41: Bars | C41: Profit and Loss | D41: Expenses | E41: selfEmployment.expenses.businessGift | F41: Review | G41: "Was this purchase for trade purposes?" | H41: Add back to income
A42: Gifts & Donations | B42: Gift | C42: Profit and Loss | D42: Expenses | E42: 0 | F42: Review | G42: "Was this donation made personally using Gift Aid or paid directly from your business account?" | H42: If directly paid from busines account then not for trade, disallow and add back to income.
A43: Gifts & Donations | B43: Charity | C43: Profit and Loss | D43: Expenses | E43: capitalGains.disposals.proceeds | F43: Review | G43: "Did you tick the gift aid box when making this donation?" | H43: If yes allowable, if not ticked then do not include this donation in calculations - Do not add back to income either as its not disallowable.
A44: Investments | B44: Equities | C44: Profit and Loss | D44: Expenses | E44: interest.incomeFromUkBanksAndBuildingSocieties | F44: Review | G44: "Was this purchase for trade purposes?" | H44: If not for trade, then disallow and add back to income. - Prompt user to add receipt for VAT or just evidence
A45: Investments | B45: Bonds | C45: Profit and Loss | D45: Expenses | E45: interest.incomeFromUkBanksAndBuildingSocieties | F45: Review | G45: "Was this purchase for trade purposes?" | H45: If not for trade, then disallow and add back to income. - Prompt user to add receipt for VAT or just evidence
A46: Investments | B46: Bank products | C46: Profit and Loss | D46: Expenses | E46: 0 | F46: Review | G46: "Was this purchase for trade purposes?" | H46: If not for trade, then disallow and add back to income. - Prompt user to add receipt for VAT or just evidence
A47: Investments | B47: Retirement | C47: Profit and Loss | D47: Expenses | E47: pension.incomeAnnuities | F47: Review | G47: "Was this purchase for trade purposes?" | H47: If not for trade, then disallow and add back to income. - Prompt user to add receipt for VAT or just evidence
A48: Investments | B48: Annuities | C48: Profit and Loss | D48: Expenses | E48: capitalGains.disposals.proceeds | F48: Review | G48: "Was this purchase for trade purposes?" | H48: If not for trade, then disallow and add back to income. - Prompt user to add receipt for VAT or just evidence
A49: Investments | B49: Real-estate | C49: Profit and Loss | D49: Expenses | E49: selfEmployment.expenses.advertisingOrMarketing | F49: Review | G49: "Was this purchase for trade purposes?" | H49: If not for trade, then disallow and add back to income. - Prompt user to add receipt for VAT or just evidence
A50: Bills & Utilities | B50: Television | C50: Profit and Loss | D50: Expenses | E50: selfEmployment.expenses.adminCosts | F50: Review | G50: "Was this purchase for trade purposes?" | H50: If not for trade, then disallow and add back to income. - Prompt user to add receipt for VAT or just evidence
A51: Bills & Utilities | B51: Home Phone | C51: Profit and Loss | D51: Expenses | E51: selfEmployment.expenses.adminCosts | F51: Allowable | H51: Deduct from expenses
A52: Bills & Utilities | B52: Internet | C52: Profit and Loss | D52: Expenses | E52: selfEmployment.expenses.adminCosts | F52: Allowable | H52: Deduct from expenses
A53: Bills & Utilities | B53: Mobile Phone | C53: Profit and Loss | D53: Expenses | E53: selfEmployment.expenses.premisesRunningCosts | F53: Allowable | H53: Deduct from expenses
A54: Bills & Utilities | B54: Utilities | C54: Profit and Loss | D54: Expenses | E54: selfEmployment.expenses.motorExpenses | F54: Allowable | H54: Deduct from expenses
A55: Auto & Transport | B55: Auto Insurance | C55: Profit and Loss | D55: Expenses | E55: selfEmployment.expenses.motorExpenses | F55: Allowable | H55: Deduct from expenses
A56: Auto & Transport | B56: Auto Payment | C56: Profit and Loss | D56: Expenses | E56: selfEmployment.expenses.travelCosts | F56: Allowable | H56: Deduct from expenses
A57: Auto & Transport | B57: Parking | C57: Profit and Loss | D57: Expenses | E57: selfEmployment.expenses.travelCosts | F57: Review | G57: "Was this paying to park your car…or paying for parking it badly?" | H57: If parking fine DISALLOW. If not then deduct
A58: Auto & Transport | B58: Public transport | C58: Profit and Loss | D58: Expenses | E58: selfEmployment.expenses.motorExpenses | F58: Allowable | H58: Deduct from expenses
A59: Auto & Transport | B59: Service & Auto Parts | C59: Profit and Loss | D59: Expenses | E59: selfEmployment.expenses.travelCosts | F59: Review if over >1,000 | G59: "Could this be a vehicle purchase?" - If user says no - "Was this purchase for trade purposes?" | H59: If Yes to vehicle purchase, then proceed Capital allowancesquestions (in capital allowance page) if yes for trade, deduct from expenses
A60: Auto & Transport | B60: Taxi | C60: Profit and Loss | D60: Expenses | E60: selfEmployment.expenses.motorExpenses | F60: Allowable | H60: Deduct from expenses
A61: Auto & Transport | B61: Gas & Fuel | C61: Profit and Loss | D61: Expenses | E61: selfEmployment.expenses.travelCosts | F61: Allowable | H61: Deduct from expenses
A62: Travel | B62: Air Travel | C62: Profit and Loss | D62: Expenses | E62: selfEmployment.expenses.travelCosts | F62: Allowable | H62: Deduct from expenses
A63: Travel | B63: Hotel | C63: Profit and Loss | D63: Expenses | E63: selfEmployment.expenses.travelCosts | F63: Allowable | H63: Deduct from expenses
A64: Travel | B64: Rental Car & Taxi | C64: Profit and Loss | D64: Expenses | E64: 0 | F64: Allowable | H64: Deduct from expenses
A65: Travel | B65: Vacation | C65: Profit and Loss | D65: Expenses | E65: selfEmployment.expenses.financialCharges | F65: Review | G65: "Was this purchase for trade purposes?" | H65: If not for trade, then disallow and add back to income. - Prompt user to add receipt for VAT or just evidence
A66: Fees & Charges | B66: Service Fee | C66: Profit and Loss | D66: Expenses | E66: selfEmployment.expenses.financialCharges | F66: Allowable | H66: Deduct from expenses
A67: Fees & Charges | B67: Late Fee | C67: Profit and Loss | D67: Expenses | E67: selfEmployment.expenses.financialCharges | F67: Disallowable | H67: Add back to income
A68: Fees & Charges | B68: Finance Charge | C68: Profit and Loss | D68: Expenses | E68: selfEmployment.expenses.financialCharges | F68: Allowable | H68: Deduct from expenses
A69: Fees & Charges | B69: ATM Fee | C69: Profit and Loss | D69: Expenses | E69: selfEmployment.expenses.financialCharges | F69: Disallowable | H69: Add back to income
A70: Fees & Charges | B70: Bank Fee | C70: Profit and Loss | D70: Expenses | E70: selfEmployment.expenses.commissions | F70: Allowable | H70: Deduct from expenses
A71: Fees & Charges | B71: Commissions | C71: Profit and Loss | D71: Expenses | E71: 0 | F71: Allowable | H71: Deduct from expenses
A72: Fines & Penalties | B72: Fines & Penalties | C72: Profit and Loss | D72: Expenses | E72: selfEmployment.expenses.advertisingOrMarketing | F72: Disallowable | H72: Add back to income
A73: Business Services | B73: Advertising | C73: Profit and Loss | D73: Expenses | E73: selfEmployment.expenses.professionalFees | F73: Allowable | H73: Deduct from expenses
A74: Business Services | B74: Financial Services | C74: Profit and Loss | D74: Expenses | E74: selfEmployment.expenses.adminCosts | F74: Allowable | H74: Deduct from expenses
A75: Business Services | B75: Office Supplies | C75: Profit and Loss | D75: Expenses | E75: selfEmployment.expenses.adminCosts | F75: Allowable | H75: Deduct from expenses
A76: Business Services | B76: Printing | C76: Profit and Loss | D76: Expenses | E76: selfEmployment.expenses.carriage | F76: Allowable | H76: Deduct from expenses
A77: Business Services | B77: Shipping | C77: Profit and Loss | D77: Expenses | E77: selfEmployment.expenses.professionalFees | F77: Allowable | H77: Deduct from expenses
A78: Business Services | B78: Legal Fees | C78: Profit and Loss | D78: Expenses | E78: selfEmployment.expenses.professionalFees | F78: Allowable | H78: Deduct from expenses
A79: Personal Services | B79: Advisory and Consulting | C79: Profit and Loss | D79: Expenses | E79: selfEmployment.expenses.professionalFees | F79: Allowable | H79: Deduct from expenses
A80: Personal Services | B80: Financial Services | C80: Profit and Loss | D80: Expenses | E80: 0 | F80: Allowable | H80: Deduct from expenses
A81: Taxes | B81: Council Tax | C81: Balance Sheet | D81: Taxation | E81: 0 | F81: N/A | H81: Just record in Financial statements LEAVE OUT OF TAX CALCULATIONS
A82: Taxes | B82: Income Tax | C82: Balance Sheet | D82: Taxation | E82: 0 | F82: N/A | H82: Just record in Financial statements LEAVE OUT OF TAX CALCULATIONS
A83: Taxes | B83: Corporation Tax | C83: Balance Sheet | D83: Taxation | E83: 0 | F83: N/A | H83: Just record in Financial statements LEAVE OUT OF TAX CALCULATIONS
A84: Taxes | B84: Value Added Tax | C84: Balance Sheet | D84: Taxation | E84: 0 | F84: N/A | H84: Just record in Financial statements LEAVE OUT OF TAX CALCULATIONS
A85: Taxes | B85: National Insurance Contributions | C85: Balance Sheet | D85: Taxation | E85: 0 | F85: N/A | H85: Just record in Financial statements LEAVE OUT OF TAX CALCULATIONS
A86: Gambling | B86: Betting | C86: Profit and Loss | D86: Expenses | E86: 0 | F86: Disallowable | H86: Add back to income
A87: Gambling | B87: Lottery | C87: Profit and Loss | D87: Expenses | E87: 0 | F87: Disallowable | H87: Add back to income
A88: Gambling | B88: Casino | C88: Profit and Loss | D88: Expenses | E88: selfEmployment.expenses.premisesRunningCosts | F88: Disallowable | H88: Add back to income
A89: Home | B89: Rent | C89: Profit and Loss | D89: Expenses | E89: selfEmployment.expenses.interestOnBankOtherLoans | F89: Allowable | H89: Deduct from expenses
A90: Home | B90: Mortgage Costs | C90: Profit and Loss | D90: Expenses | E90: selfEmployment.expenses.interestOnBankOtherLoans | F90: Review (If same amount goues out to bank or building society monthly) | G90: "You may be eligible for mortgage interest relief, since your income is an FHL, Can I have a breakdown of the mortgage interest on these payments? These are 100% deductible and will save you tax!" Then also give user as option to ask where they can get this information - "If you do not have this on your Lender's online portal, please ask them for a copy of this document. We would also need to retain this for HMRC" | H90: If uploaded by user OCR detects Interest element and records the amount relating to te tax year.
A91: Home | B91: Secured loans | C91: Profit and Loss | D91: Expenses | E91: selfEmployment.expenses.interestOnBankOtherLoans | F91: Review | G91: "Was this cost for trade purposes?" | H91: If not for trade, then disallow and add back to income. - Prompt user to add receipt for VAT or just evidence
A92: Home | B92: Mortgage Interest | C92: Profit and Loss | D92: Expenses | E92: pensions.reliefAtSource | F92: Split out when user states interest amount on payment | G92: "You may be eligible for mortgage interest relief, since your income is an FHL, Can I have a breakdown of the mortgage interest on these payments? These are 100% deductible and will save you tax!" Then also give user as option to ask where they can get this information - "If you do not have this on your Lender's online portal, please ask them for a copy of this document. We would also need to retain this for HMRC" | H92: If uploaded by user OCR detects Interest element and records the amount relating to the tax year.
A93: Pensions and Insurances | B93: Pension payments (UK Registered) | C93: Profit and Loss | D93: Expenses | E93: 0 | F93: Allowable | H93: Deduct from expenses
A94: Pensions and Insurances | B94: Pension payments (Not - UK Registered) | C94: Profit and Loss | D94: Expenses | E94: 0 | F94: N/A | G94: "Is this a private pension provider?, If so there will be no relief on this transaction, try contributing to a UK registered pension provider to reduce your tax liability." | H94: Just record in Financial statements LEAVE OUT OF TAX CALCULATIONS
A95: Pensions and Insurances | B95: Life insurance | C95: Profit and Loss | D95: Expenses | E95: selfEmployment.expenses.insurance | F95: Allowable | H95: Deduct from expenses
A96: Pensions and Insurances | B96: Buildings and contents insurance | C96: Profit and Loss | D96: Expenses | E96: 0 | F96: Allowable | H96: Deduct from expenses
A97: Pensions and Insurances | B97: Health insurance | C97: Profit and Loss | D97: Expenses | E97: selfEmployment.expenses.staffCosts | F97: Allowable | H97: Deduct from expenses
A98: *Based on merchant or ML | B98: Salaries | C98: Profit and Loss | D98: Expenses | E98: selfEmployment.expenses.professionalFees | F98: Allowable | H98: Deduct from expenses (Check for expense being over £1k) - If over £1K, likely to be Salary PAID ,which is allowable, - ALSO CHECK IF SALARY IS BEING SENT TO PARTNER (IF RECIPIENT NAME MATCHES partner name in any way, take this as drawings and change the share allocation {Check drawings calculations tab})
A99: *Based on merchant or ML | B99: HR Fees | C99: Profit and Loss | D99: Expenses | E99: selfEmployment.expenses.professionalFees | F99: Allowable | H99: Deduct from expenses
A100: *Based on merchant or ML | B100: Accounting Fees | C100: Profit and Loss | D100: Expenses | E100: #N/A | F100: Allowable | H100: Deduct from expenses
...

Sheet Remittance Basis rules
A1: Remittance Basis Charge | B1: Only activate when user chooses "Foreign income" as income category - Regardless of sub-inome category
B2: £
A3: Resident Years | B3: Annual Charge
A4: 0-7 Years | B4: Free | D4: API Name: | E4: foreignIncome.remittanceBasis
A5: 7 - 9 years | B5: 30000
A6: 12 to 14 years | B6: 60000
A7: 15 to 20 Years | B7: UK-Dom - Tax as normal with PA - Cannot claim RBA | D7: Prompt to user: | E7: "How long have you been resident in the uk?"
A9: If you do not remit the funds back to the UK, you can claim remittance basis relief - If a UK resident and non domiciled
A11: Residence Test
C12: Bank Feed | D12: AI ML Indication | E12: Percentage | F12: What does this mean | G12: AI Flag:
A13: >183 days (being 365 divided by 2 - More than half the days of the year) | B13: Then Tax resident | C13: Check how many UK transactions in a day if everyday UK transactions are daily, then UK Then Domicile | D13: UK resident and foreign income chosen - Can use Remittance basis | E13: If UK transactions >50% in a day we put UK, check IBAN (if GB….) - We check each day what transactions are country predominant | F13: If you are tax resident, your worldwide income is subject to UK tax, unless you claim the remittance basis. | G13: If daily transations read "UK" for more than 50% of the year then UK Resident.
A14: <183 Days | B14: Check residence ties | C14: If more transations out of the UK, then trigger non-domicile | D14: Non -UK resident and foreign income - Cannot use Remittance basis | E14: If UK transactions <50% in a day we put Foreign, check IBAN (if GB….) - We check each day what transactions are foreign predominant | F14: Use Personal allowance tax as normal | G14: If daily transactions read "Foreign" for more than 50% then UK non resident and can claim RBA charge rules
A18: 1. GLOBAL RESIDENCE & DOMICILE CHECK
B19: Domicile? | C19: If Home address based in the UK upon user setup
A20: IF user is NOT UK tax resident: (<183 days per year) | B20: Residency? | C20: IBAN tracker result on days in the UK
A21: → Do NOT apply UK tax rules on foreign income
B22: Ask User- "How long have you been living in the UK?"
A23: ELSE IF user is UK tax resident AND UK domiciled: (Check rules above - Cell A14 and A15)
A24: → Tax ALL worldwide income and gains under the ARISING BASIS | B24: Less than 7 years | C24: NO RBC
B25: 7-11 Years | C25: RBC = £30k
B26: 12 - 14 years | C26: RBC = £60k
A27: → Proceed to remittance logic | B27: 15 Years or more | C27: UK domiciled
A29: 2. REMITTANCE BASIS LOGIC (For UK Residents who are Non-Domiciled) | E29: If User wants to claim this, but bank transations says otherwise -> ask then for evidence such as flight tickets
A31: IF user is UK resident AND non-UK domiciled THEN:
A32: IF foreign income/gains < £2,000 PER ANNUM AND no remittances paid into a UK bank account:
A33: → Automatically apply remittance basis
A34: → No RBC (Remittance Basis Charge), no claim needed
A35: → Do NOT tax unremitted income/gains
A37: ELSE IF user claims remittance basis:
A38: → IF user has been UK resident:
A39: - 0+ of last 7 years → RBC = £0
A40: - 7+ of last 9 years → RBC = £30,000
A41: - 12+ of last 14 years → RBC = £60,000
A42: - 15+ of last 20 years → NOT ALLOWED (deemed domiciled)
A43: → Tax only:
... A63: 4. FOREIGN INCOME TYPES – RULES & FORMS
A64: Income Type | B64: Tax Logic Summary
A65: Foreign Employment | B65: Tax on arising basis if UK duties; remittance basis only if work abroad + paid abroad
A66: Foreign Self-Employment | B66: Remittance basis allowed if earned abroad + not remitted
A67: Foreign Dividends | B67: Remittance basis allowed if not remitted to UK
A68: Foreign Bank Interest | B68: Remittance basis allowed if not remitted to UK
A69: Foreign Property Income | B69: Remittance basis allowed if income earned abroad and not remitted
A70: Foreign Capital Gains | B70: Remittance basis allowed if gains on foreign assets not remitted
A71: Foreign Pensions | B71: Usually taxed on arising basis
A72: Crypto (foreign held) | B72: Treated as foreign asset – remittance basis if not remitted
A73: Trust Income (offshore) | B73: Remittance basis if unremitted – complex, flag for review
A74: 5. REMITTANCE FLAG
A76: IF bank feeds show foreign income is remitted to the UK":
A77: → Remitted = Taxable
A79: ELSE:
A80: → Unremitted = Not taxable if remittance basis applies
A82: 6. DATA FLAGS FOR FRONTEND INTAKE
A83: Field | B83: Value | C83: Logic Triggered
A84: is_uk_tax_resident | B84: true/false | C84: Applies UK tax logic
A85: is_non_domiciled | B85: true/false | C85: Enables remittance logic
A86: claim_remittance_basis | B86: true/false | C86: Triggers remittance logic + RBC check
A87: foreign_income_amount | B87: £ amount | C87: If ≥ £2,000 → claim needed
A88: foreign_income_remitted | B88: true/false | C88: If true → tax it
A89: foreign_income_type | B89: employment, dividends, etc. | C89: Directs to appropriate SA form logic
A90: employment_duties_location | B90: UK or Abroad | C90: If UK → no remittance allowed
A91: years_of_uk_residency | B91: Number (0–20) | C91: Triggers RBC or deemed domicile logic

Sheet Loss Relief
A1: Loss Relief
A2: 1)
A3: Through HMRC API to see if this is claimed or not - Take the Brought Forward losses (the pool) - From API and TYPE of trading loss - And the type of claim made (check previous SA100) - LOOK AT THE METHOD OF LOSS RELIEF USING GET HMRC API - LOOK FOR "RELEVANT RELIEF IN CALCULATION"
A5: Loss = If allowable expenses and capital allowances supersedes the taxable income made in that tax year
A7: Income types | B7: Allowance | C7: API Name | D7: Applicable to: | E7: Prompt: | F7: Calculation | G7: How to apply: | H7: AI Flag:
A8: Income Loss (Applied to all income types but capital gains) | B8: Same-year relief | C8: lossesAppliedToGeneralIncome | D8: Self-employment, employment income, property, FHL | E8: "Did you make a loss this year and want to reduce this year’s tax bill?" | F8: 1. Take total income from self emplyment and property income sources 2. Subtract business loss 3. Apply personal allowance to remaining income | G8: Offset against total income in current year (before personal allowance) | H8: Offset against total income if user says "Yes", in current year before tax bands. - also if it is expected that a loss will be made in the year, then let user know. If this applies then IB should ask whether they should apply this. - If they have no other qualifying income to offset against, then carry forward or previous year.
B9: Carry back to previous year | C9: lossesCarriedBackToPreviousYear | D9: Self-employment, FHL | E9: Did you make a loss and want to apply it to reduce last year’s income tax bill? | F9: 1. Retrieve previous year’s income 2. Subtract current year loss from that amount 3. Recalculate prior year tax | G9: If income in previous year was higher or loss is early year loss | H9: Calculate prior year tax & apply relief in current return - then we amend last financial year retun IF deadline for last return is not up yet.
B10: Carry forward | C10: lossesCarriedForward | D10: Self-employment, employment income, property, FHL | E10: Would you prefer to store this loss and use it in a future tax year when your profits return? | F10: 1. Record unused loss (asked to user on setup) 2. Track by trade/source 3. Apply automatically when next profit arises in same trade | G10: When no current/prior year relief is chosen | H10: Store loss by source for future year offset - if loss made in that year
B11: Early years loss relief | C11: earlyTradeLossesRelief | D11: New self-employment | E11: Is this your first 4 years of trading and you made a loss? | F11: 1. Start from earliest of prior 3 years 2. Apply loss to each year until used up 3. Recalculate tax for affected years | G11: Offset against income from the 3 years prior to the loss year (FIFO) | H11: Offer prompt to carry back up to 3 years (FIFO)
B12: Terminal loss relief | C12: terminalLossRelief | D12: Ceased self-employment | E12: Are you stopping your business this year and have made a loss? | F12: 1. Start from latest of prior 3 years 2. Offset loss backwards 3. Recalculate tax per year offset | G12: Offset against profits of the last 3 tax years (LIFO) | H12: Apply against prior 3 years' profits (LIFO)
A13: Capital Loss | B13: Offset against current year gains | C13: lossesUsedAgainstGains | D13: Capital gains | E13: Did you make a capital loss and want to reduce this year’s capital gains tax bill? | F13: 1. Calculate total gains 2. Subtract allowable capital losses 3. Then apply £3,000 annual CGT exemption | G13: If CGT liability exists and loss is in same year | H13: Offset against current year gains before allowance
B14: Carry forward unused losses | C14: lossesCarriedForward | D14: Capital gains | E14: Do you want to store this capital loss and use it against future capital gains? | F14: 1. Store unused loss in CGT loss pool 2. Auto apply in future gains before applying exemptions | G14: When not fully used in current year or unused loss exists | H14: Store in "loss pool" to auto-apply to future gains
A16: Examples for Each Loss Relief Type
A19: Same-Year Relief | E19: Early Years Loss Relief
A20: Maya runs a small consultancy and had £18,000 in employment income and made a £5,000 trading loss in the same year. | E20: Layla started her business in 2022 and had a £9,000 trading loss.
A22: Step-by-step: | E22: Past income:
A23: 1. Total income = £18,000 | E23: - 2019: £6,000
A24: 2. Subtract loss: £18,000 − £5,000 = £13,000 | E24: - 2020: £4,000
A25: 3. Apply personal allowance (£12,570) | E25: - 2021: £2,000
A26: 4. Taxable income = £430
E27: Step-by-step (FIFO):
A28: Only £430 is taxed instead of £5,430 (if no relief was used). | E28: 1. Offset £6,000 to 2019
A29: Carry Back to Previous Year | E29: 2. Offset £3,000 to 2020
A30: James had a trading loss of £7,000 this year. Last year, his total income was £15,000. | E30: 3. No amount left for 2021
A32: Step-by-step: | E32: Her tax is recalculated for those prior years and HMRC refunds any overpaid tax.
A33: 1. Carry back £7,000 loss to last year | E33: Terminal Loss Relief
A34: 2. Adjusted prior year income = £15,000 − £7,000 = £8,000 | E34: Ajay closed his plumbing business in 2025 and made a final-year loss of £10,000.
A35: 3. Recalculate last year’s tax based on £8,000 income
E36: Previous profits:
A37: Result: Refund due from HMRC for overpaid tax. | E37: - 2024: £5,000
A38: Carry Forward | E38: - 2023: £4,000
A39: Tariq made a £6,000 loss this year and had no other income to offset. | E39: - 2022: £3,000
A41: Step-by-step: | E41: Step-by-step (LIFO):
A42: 1. No offset this year or last year | E42: 1. Offset £4,000 to 2024 → £6,000 remaining
A43: 2. Carry forward £6,000 to future years | E43: 2. Offset £4,000 to 2023 → £2,000 remaining
A44: 3. Next year, he earns £9,000 from the same business | E44: 3. Offset £2,000 to 2022 → £0 remaining
A45: 4. Auto apply £6,000 to reduce next year’s taxable profit
E46: All three years are updated, and previous tax is refunded.
A47: Taxable profit in next year = £3,000. | E47: Offset Capital Loss Against Current Gains
E48: Maria sold shares and made a gain of £12,000. She also sold crypto and lost £4,000.
A49: Carry Forward Capital Loss
A50: Dev made a £5,000 capital loss this year but had no gains to offset. | E50: Step-by-step:
E51: 1. Net gain = £12,000 − £4,000 = £8,000
A52: Step-by-step: | E52: 2. Apply annual CGT allowance (£3,000) = £5,000 taxable gain
A53: 1. Store £5,000 in CGT loss pool
A54: 2. Next year, he makes a £10,000 gain on property | E54: She only pays CGT on £5,000 instead of £9,000.
A55: 3. Apply £5,000 loss first → only £5,000 gain remains
A56: 4. Apply £3,000 CGT exemption → £2,000 taxable
A58: Only £2,000 is subject to CGT.

Sheet Loss Relief scenarios
A1: Loss Relief Recommendation Scenarios – IntelliBooks
A3: IB must use the below scenarios to give the bext tax saving relief.
A4: Scenario | B4: Recommended Relief | C4: Why This Works | D4: Notes | E4: Eligible Loss Relief Options | F4: API Logic Flags | G4: User can use this relief if… (eligibility) | H4: IB automation & evidence (what to check/ask) | I4: Claim window (guide) | J4: Income Tax Cap?
A5: User is in their 1st year of trading, made a loss, and had employment income in past 3 years. | B5: Early Year Loss Relief | C5: Allows loss to be carried back up to 3 years, oldest year first. Can generate a refund if previous income existed. | D5: Prompt user to enter prior year incomes or upload old SA100s. | E5: - Early Year Loss Relief - Carry Forward (optional) - Same-Year Relief (if income exists) | F5: earlyTradeLossRelief, lossesCarriedForward, lossesAppliedToGeneralIncome | G5: • The loss arose in one of the **first four tax years** of the trade. • The trade is run **commercially with a view to profit** (not a hobby). • Relief set **against total income of the 3 years before the loss year**, **earliest year first**. • Subject to the **Income Tax reliefs cap**; non‑active restrictions do not usually apply to sole traders. | H5: • Confirm **trade start date** and loss year. • Pull **prior 3 years’ income** from HMRC or ask for SA100s/P60s. • Flag if ANI relief‑cap may bite; show estimated cap. • Ensure no duplicate claims already made for the same loss. | I5: Claim within HMRC time limits (typically by 31 Jan two years after the loss year’s end). | J5: Yes
A6: User closed their business this year and has made a large loss. | B6: Terminal Loss Relief | C6: Can apply loss to final 3 years' profits, most recent year first. Ideal for ending businesses. | D6: Must have had trading profits in previous years to benefit. | E6: - Terminal Loss Relief - Carry Forward (if not all used) - Same-Year Relief (if income exists) | F6: terminalLossRelief, lossesCarriedForward, lossesAppliedToGeneralIncome | G6: • The trade **ceased permanently** in the year, and a **terminal loss** exists (loss in the **final 12 months** plus allowable adjustments). • May be **carried back 3 years** **against profits of the same trade**, **latest year first**. | H6: • Capture **cessation date** and final period accounts. • Confirm there is no intention to resume (avoid temporary pause). • Retrieve **last 3 years’ trading profits** of the same trade. • Compute the statutory **terminal‑loss figure** from the last 12 months. | I6: Within HMRC claim limits following the cessation tax year (IB to track & alert). | J6: No
A7: User made a loss but already filed last year’s return more than 12 months ago. | B7: Carry Forward Loss Relief | C7: Carry forward ensures relief isn't lost and can reduce tax when profits return. | D7: Carry forward automatically tracked by IntelliBooks until used. | E7: - Carry Forward - Same-Year Relief (if income exists) | F7: lossesCarriedForward, lossesAppliedToGeneralIncome | G7: • There is an **unused trading loss** and the user **doesn’t** claim sideways/carry‑back. • Loss will be set **against the next profits of the same trade** (mandatory use when profits arise, unless a valid restriction applies). | H7: • Maintain a **loss pool** per trade. • On next profit: **auto‑apply** against that trade before other reliefs. • Persist evidence: final computation of original loss and any partial uses. | I7: No separate claim needed once recorded; ensure loss notified within normal time limits. | J7: No
A8: User wants to reduce this year’s tax bill from employment or other income. | B8: Same-Year Loss Relief | C8: Loss reduces current total income before applying the personal allowance. | D8: Only applies if user has other taxable income in same year. | E8: - Same-Year Relief only | F8: lossesAppliedToGeneralIncome | G8: • A **commercial trading loss** arose this year. • User wants to **reduce total income this year** (employment, pensions, savings, etc.). • Subject to **reliefs cap** and **non‑active/LLP ‘at‑risk’** restrictions where relevant. | H8: • Check **commercial purpose** declaration. • Pull **other‑income totals** for the year. • Apply **reliefs cap** simulation (greater of £50k or 25% ANI). • For partners: check **non‑active/at‑risk** status before allowing sideways relief. | I8: Claim by normal time limit for the loss year (IB shows deadline and drafts claim wording). | J8: Yes
A9: User has not filed last year’s return and made a loss this year. | B9: Carry Back to Previous Year | C9: If prior year income was high, this gives immediate tax saving or refund. | D9: Can be applied directly in SA100 or as amendment if return already submitted recently. | E9: - Carry Back to Previous Year - Same-Year Relief - Carry Forward (optional) | F9: lossesCarriedBackToPreviousYear, lossesAppliedToGeneralIncome, lossesCarriedForward | G9: • A **commercial trading loss** arose in the current year. • User wants to **relieve against last year’s total income** (often to trigger a **repayment**). • Subject to **reliefs cap**; must be within the carry‑back rules for timing. | H9: • Check last year’s return status: filed? within **amendment window**? • Retrieve last year’s **total income and tax paid** from HMRC. • Simulate same‑year vs carry‑back to show **best tax outcome**. | I9: Claim within the normal time limit for the loss year; amend prior year if still in window. | J9: Yes
A10: User made a capital loss this year and also made a capital gain. | B10: Offset Capital Loss | C10: Offsets current year loss before applying CGT exemption. Reduces tax bill now. | D10: Order: capital loss → gain → then £3k exemption. | E10: - Offset Capital Loss - Carry Forward Capital Loss (if any balance) | F10: lossesUsedAgainstGains, lossesCarriedForward | G10: • User has **chargeable gains** this year and also **capital losses** this year or brought forward. • **Losses must be set** against gains **before** the Annual Exempt Amount; cannot preserve AEA by restricting losses. | H10: • Collect **disposal computations** (proceeds, cost, incidental costs). • Compute **net gains** after offset; then apply **AEA**. • Store any **unused losses** for carry‑forward. | I10: Report capital losses within HMRC time limits to establish them (normally up to 4 years after the tax year). | J10: No
A11: User made a capital loss but had no capital gain this year. | B11: Carry Forward Capital Loss | C11: Loss saved to reduce CGT in future years. | D11: IntelliBooks will track and auto-apply to future gains. | E11: - Carry Forward Capital Loss only | F11: lossesCarriedForward | G11: • There are **no gains** this year (or not enough to absorb losses). • Unused capital losses are **carried forward** to future gains (no carry‑back except special cases like death/estate). | H11: • Record the **loss figure** and the **year** it arose. • On future gains, IB **auto‑offsets** carried‑forward losses first, then applies AEA. | I11: Report capital losses within HMRC time limits to establish them (normally up to 4 years after the tax year). Loss must be **claimed/registered** within HMRC time limits (typically up to 4 years). | J11: No

Sheet Income Tax reliefs cap
A1: CAP=
A2: The greater of £50,000 or 25% of your Adjusted total income (ATI) for that year
A4: How does the rule work?
A5: 1) What ATI is used for
A6: HMRC caps some reliefs that are set against total income (e.g., sideways loss relief). The annual cap per person is:
A7: Cap = max(£50,000, 25% × ATI).
A8: ATI is only needed if total income may exceed ~£200,000; otherwise the cap defaults to £50,000.
A10: 2) Simple ATI formula (for the reliefs cap)
A11: Start with total taxable income before Personal Allowance, then adjust as follows:
A12: ATI = Total income (pre‑PA)
A13: − gross personal pension contributions where relief is given at source (net×100/80)
A14: − retirement annuity payments
... A28: • Carry‑forward trading losses against future profits of the same trade.
A29: • Capital losses (CGT regime). | E29: If User wants to claim this, but bank transations says otherwise -> ask then for evidence such as flight tickets
A30: • Pension contributions (Relief‑at‑Source) and Gift Aid donations themselves.
A32: 4) IntelliBooks application steps
A33: 1) Compute ATI using the formula above.
A34: 2) Compute Cap = max(£50,000, 25% × ATI).
A35: 3) Sum all reliefs that are within the cap this year (e.g., sideways/early‑years/carry‑back losses).
A36: 4) Allow up to the cap now; any excess trading loss → carry‑forward pool (or consider carry‑back if still in time).
A38: 5) Worked Example — Sole Trader
A39: Facts (2024/25):
A40: • Trading profit (SA103): £72,000; Bank interest: £800; Dividends: £2,000.
A41: • Personal pension (Relief‑at‑Source): £4,000 net (gross £5,000).
A42: • Payroll Giving deducted by employer: £600.
A43: • Gift Aid donations: £800 net (gross £1,000) — ignore for ATI (but affects ANI/bands).
... A49: Step 5: £20,000 of the loss remains → carry forward against future profits of that trade (or consider carry‑back).

Sheet 4. Allowable and Disallowable
B1: Including foreign income of each
B2: Self Employment Income | D2: Property Income (Commercial Property) | F2: Property Income (Commercial Property rest of world) | H2: Property Income (Residential Property) | J2: Property Income (FHL based in UK) | L2: Property Income (Rent-A-Room) | N2: Capital Gains
B3: Allowable Expenses | C3: Disallowable Expenses | D3: Allowable Expenses | E3: Disallowable Expenses | F3: Allowable Expenses | G3: Disallowable Expenses | H3: Allowable Expenses | I3: Disallowable Expenses | J3: Allowable Expenses | K3: Disallowable Expenses | L3: Allowable Expenses | M3: Disallowable Expenses | N3: Allowable Expenses | O3: Disallowable Expenses

Sheet API for past returns
A1: { | B1: AI trigger for application of relief/Allowance
A2: "metadata": {
A3: "calculationId": "f2fb30e5-4ab6-4a29-b3c1-c7264259ff1c",
A4: "taxYear": "2021-22",
A5: "requestedBy": "customer",
A6: "requestedTimestamp": "2021-02-15T09:35:15.094Z",
A7: "calculationReason": "customer-request",
A8: "calculationTimestamp": "2021-08-15T09:35:15.094Z",
A9: "calculationType": "final-declaration",
A10: "intentToSubmitFinalDeclaration": true,
A11: "finalDeclaration": true,
A12: "finalDeclarationTimestamp": "2021-02-15T09:35:15.094Z",
A13: "periodFrom": "2021-04-06",
... A21: "statePensionAgeDate": "2050-04-06",
A22: "studentLoanPlan": [ | B22: Student Loan Plan 1 calculation | C22: Only use if last tax return has this relief claimed, and put this in tax return as well as daily calculation
A23: {
A24: "planType": "plan1" | B24: Student Loan Plan 1 calculation | C24: Only use if last tax return has this relief claimed, and put this in tax return as well as daily calculation
A25: }
A26: ],
A27: "class2VoluntaryContributions": true, | B27: Always applied if rules are met | C27: Only use if last tax return has this relief claimed, and put this in tax return as well as daily calculation
A28: "marriageAllowance": "transferor", | B28: Apply marriage allowance (IB will ask user if the income of the partner still remais the same) | C28: Only use if last tax return has this relief claimed, and put this in tax return as well as daily calculation
A29: "uniqueTaxpayerReference": "AGvHTfRUPO",
A30: "itsaStatus": "No Status"
A31: },
A32: "incomeSources": {
A33: "businessIncomeSources": [
A34: {
A35: "incomeSourceId": "XBIS12345678910",
A36: "incomeSourceType": "self-employment", | B36: Shows us that Income on Self Employment Income (Can suggest this upon setup of income)
A37: "incomeSourceName": "Self-Employment Business One",
A38: "accountingPeriodStartDate": "2021-04-06",
A39: "accountingPeriodEndDate": "2022-04-05",
A40: "source": "MTD-SA",
A41: "cessationDate": "2021-04-06",
A42: "commencementDate": "2022-04-05",
A43: "latestPeriodEndDate": "2022-04-05",
A44: "latestReceivedDateTime": "2022-12-02T15:25:48.475Z",
A45: "submissionPeriods": [
A46: {
A47: "periodId": "001",
A48: "startDate": "2021-04-06",
... A76: ],
A77: "lossesBroughtForward": [ | B77: Trigger Loss Relief (below will tell us type of claim) | C77: Only use if last tax return has this relief claimed, and put this in tax return as well as daily calculation
A78: {
A79: "lossId": "0yriP9QrW2jTa6n",
A80: "incomeSourceId": "XBIS12345678910",
A81: "incomeSourceType": "self-employment",
A82: "submissionTimestamp": "2022-12-02T15:25:48.475Z",
A83: "lossType": "income",
A84: "taxYearLossIncurred": "2020-21",
A85: "currentLossValue": 12500, | B85: Apply this amount to next tax return IF Carry forward method has been chosen by user last tax year | C85: Only use if last tax return has this relief claimed, and put this in tax return as well as daily calculation
A86: "mtdLoss": false
A87: }
A88: ],
A89: "claims": [
A90: {
A91: "claimId": "0vayS9JrW2jTa6n",
A92: "originatingClaimId": "1vayS9JrW2jTa6p",
A93: "incomeSourceId": "000000000000210",
A94: "incomeSourceType": "self-employment",
A95: "submissionTimestamp": "2022-12-02T15:25:48.475Z",
A96: "taxYearClaimMade": "2021-22",
A97: "claimType": "carry-forward", | B97: Loss relief will be show in "claimType" - Look out for this to see how to calculate - If other rules, check loss relief tab to see how to apply of needed this year at all. | C97: Only use if last tax return has this relief claimed, and put this in tax return as well as daily calculation
A98: "sequence": 1
A99: }
A100: ],
A101: "constructionIndustryScheme": [
A102: {
A103: "employerRef": "123/AA12345",
A104: "contractorName": "Company-123 Ltd.",
A105: "periodData": [
A106: {
A107: "deductionFromDate": "2021-11-02",
A108: "deductionToDate": "2021-12-02",
A109: "submissionTimestamp": "2021-12-10T15:25:48.475Z",
A110: "source": "contractor",
A111: "deductionAmount": 5000.99 | B111: This shows us if CIS has been claimed in the past - Would help us see if we should apply this going forward - If this is the case then we do and follow CIS relief rules. | C111: Only use if last tax return has this relief claimed, and put this in tax return as well as daily calculation
A112: }
A113: ]
A114: }
A115: ],
A116: "allowancesReliefsAndDeductions": [
A117: {
A118: "type": "investment-reliefs",
A119: "submittedTimestamp": "2021-12-10T15:25:48.475Z",
A120: "startDate": "2021-11-02",
A121: "endDate": "2021-12-02",
A122: "source": "MTD-SA"
A123: }
... A149: "giftOfInvestmentsAndPropertyToCharity": 12500,
A150: "blindPersonsAllowance": 12500, | B150: Apply Blind person allowance if claimed in the past (The situation of the person is not likely to change) - Also apply in daily tax calculations | C150: Only use if last tax return has this relief claimed, and put this in tax return as well as daily calculation
A151: "lossesAppliedToGeneralIncome": 12500,
A152: "cgtLossSetAgainstInYearGeneralIncome": 12500, | B152: If we see this, we look at CGT loss relief rules - If "cgtLossSetAgainstInYearGeneralIncome" this would be CGT loss that will be deducted against all other income to reduce tax liability | C152: Only use if last tax return has this relief claimed, and put this in tax return as well as daily calculation
A153: "qualifyingLoanInterestFromInvestments": 5000.99,
A154: "postCessationTradeReceipts": 5000.99,
A155: "paymentsToTradeUnionsForDeathBenefits": 5000.99,
A156: "grossAnnuityPayments": 5000.99,
A157: "annuityPayments": {
A158: "reliefClaimed": 5000.99,
A159: "rate": 20.99
...

Sheet C
A1: TRANSACTION CATEGORIES AND OTHER INFORMATION FOR AUTOMATIC ML BANK CATEGORISATION

Sheet List of Pension providers (UK)
A1: Registered UK Pension Providers
A2: AVIVA
A3: Scottish Widows
A4: Legal & General
A5: Nest Pensions
A6: PensionBee
A7: Standard Life
A8: Royal London
A9: Aegon UK
A10: Hargreaves Lansdown
A11: Fidelity International
A12: True Potential Investments
... A26: Barnett Waddingham

Sheet List of Charities (Gift Aid)
A1: Gift Aid Eligible Charity Name
A2: Cancer Research UK
A3: NSPCC
A4: British Red Cross
A5: Macmillan Cancer Support
A6: Oxfam GB
A7: Save the Children
A8: British Heart Foundation
A9: Marie Curie
A10: Mind (National Association for Mental Health)
A11: Shelter
A12: RSPCA
... A51: Médecins Sans Frontières UK

Sheet List of CIS contracting compani
A1: Known CIS Contractor (UK)
A2: Balfour Beatty
A3: Laing O’Rourke
A4: Skanska UK
A5: Mace Group
A6: Kier Group
A7: Costain Group
A8: Galliford Try
A9: Morgan Sindall
A10: Wates Group
A11: ISG Ltd
A12: Interserve
... A32: Other
